Workbook

Sheet Painel
B1: Valuation de Vale, CSN e Gerdau
B2: Escolha a empresa e o cenário nas células amarelas. Todas as abas recalculam.
B3: Estudo acadêmico e de portfólio, com dados públicos da CVM e da B3. Não é recomendação de compra ou venda. As premissas são uma proposta por regra, ainda não revisada.
X4: Listas (não apagar)
B5: Empresa | D5: Vale (VALE3) | G5: ← clique na célula e escolha na lista | X5: Vale (VALE3) | Y5: =MATCH($D$5,$X$5:$X$7,0) -> 1
B6: Cenário | D6: Moderado | G6: ← clique na célula e escolha na lista | X6: CSN (CSNA3)
X7: Gerdau (GGBR4)
B9: As três variáveis do cenário | C9: Em uso | D9: Pessimista | E9: Moderado | F9: Otimista | G9: Ajuste manual | H9: Partida | X9: Pessimista | Y9: =MATCH($D$6,$X$9:$X$11,0) -> 2
B10: Crescimento da receita, ao ano | C10: =IF(ISNUMBER(G10),MIN(MAX(G10,MIN(D10:F10)),MAX(D10:F10)),CHOOSE(Painel!$Y$9,D10,E10,F10)) -> 0.0378 | D10: =Premissas!$D$7 -> 0 | E10: =Premissas!$E$7 -> 0.0378 | F10: =Premissas!$F$7 -> 0.0683 | H10: =Premissas!$C$7 -> 0.0209 | X10: Moderado
B11: Margem EBITDA em 2030 | C11: =IF(ISNUMBER(G11),MIN(MAX(G11,MIN(D11:F11)),MAX(D11:F11)),CHOOSE(Painel!$Y$9,D11,E11,F11)) -> 0.3936 | D11: =Premissas!$D$8 -> 0.3484 | E11: =Premissas!$E$8 -> 0.3936 | F11: =Premissas!$F$8 -> 0.4542 | H11: =Premissas!$C$8 -> 0.3459 | X11: Otimista
B12: WACC (taxa de desconto) | C12: =IF(ISNUMBER(G12),MIN(MAX(G12,MIN(D12:F12)),MAX(D12:F12)),CHOOSE(Painel!$Y$9,D12,E12,F12)) -> 0.13117675 | D12: =WACC!$D$19+Premissas!$D$9 -> 0.14677675 | E12: =WACC!$D$19+Premissas!$E$9 -> 0.13117675 | F12: =WACC!$D$19+Premissas!$F$9 -> 0.11557675 | H12: =WACC!$D$19 -> 0.13117675
B13: Ajuste manual: digite um valor entre o pessimista e o otimista (ex.: 5%) para testar um meio-termo; deixe vazio para usar o cenário. Partida é o nível de hoje.
B15: Resultado | C15: Valor | D15: O que é
B16: Preço justo por ação | C16: ='Valor justo'!D29 -> 94.944606 | D16: Quanto vale cada ação segundo o modelo, no cenário em uso.
B17: Preço de mercado | C17: ='Valor justo'!D30 -> 67.64 | D17: Último fechamento na B3.
B18: Diferença para o mercado | C18: ='Valor justo'!D31 -> 0.40367543 | D18: Preço justo ÷ preço de mercado − 1.
B19: Valor da empresa (EV) | C19: ='Valor justo'!D22 -> 432425.19 | D19: Valor da operação inteira, em R$ milhões.
B20: Valor do acionista | C20: ='Valor justo'!D27 -> 386649.19 | D20: EV menos dívida líquida e minoritários, mais investimentos.
B21: Peso do valor terminal | C21: ='Valor justo'!D32 -> 0.75656923 | D21: Quanto do valor vem de depois de 2030.
B22: Preço pelo fluxo do acionista (FCFE) | C22: ='Valor justo'!D43 -> 81.70125 | D22: Conferência por outro caminho: deve ficar perto do preço justo.
B24: O caminho do cálculo, começando pelo FCFF | C24: Valor | D24: Onde ver
B25: 1. FCFF de 2027E: o caixa livre da empresa | C25: =FCFF!E13 -> 27056.553 | D25: Aba FCFF
B26: 2. WACC: a taxa que traz o futuro a valor de hoje | C26: =WACC!D22 -> 0.13117675 | D26: Aba WACC
B27: 3. Fluxos de 2026 a 2030, a valor de hoje | C27: ='Valor justo'!D21 -> 105265.59 | D27: Aba Valor justo
B28: 4. Tudo o que vem depois de 2030, a valor de hoje | C28: ='Valor justo'!D18 -> 327159.59 | D28: Aba Valor justo
B29: 5. Valor da empresa (3 + 4) | C29: ='Valor justo'!D22 -> 432425.19 | D29: Aba Valor justo
B30: 6. Valor do acionista (5 − dívida líquida − minoritários + investimentos) | C30: ='Valor justo'!D27 -> 386649.19 | D30: Aba Valor justo
B31: 7. Preço justo (6 ÷ número de ações) | C31: ='Valor justo'!D29 -> 94.944606 | D31: A aba Passo a passo explica cada etapa

Sheet Passo a passo
B1: ="Como o preço justo é calculado - "&Painel!$D$5 -> Como o preço justo é calculado - Vale (VALE3)
B2: O valuation pelo fluxo de caixa da empresa, em sete passos. Os números são os da empresa e do cenário escolhidos no Painel e mudam junto com eles.
B4: 1. Quanto caixa a empresa gera: o FCFF
B5: Tudo começa pelo caixa livre da empresa. Pega-se o lucro da operação depois do imposto (NOPAT), soma-se a depreciação, que é custo mas não sai do caixa, e tira-se o que foi investido em ativos (capex) e em capital de giro.
B6: NOPAT de 2027E (lucro da operação depois do imposto) | C6: =FCFF!E9 -> 43038.827
B7: + Depreciação | C7: =FCFF!E10 -> 17336.088 | D7: não saiu do caixa
B8: − Capex | C8: =FCFF!E11 -> 32791.127 | D8: investimento em ativos
B9: − Variação do capital de giro | C9: =FCFF!E12 -> 527.23446 | D9: dinheiro a mais preso na operação
B10: (=) FCFF de 2027E | C10: =FCFF!E13 -> 27056.553 | D10: a aba FCFF repete a conta para cada ano
B12: 2. Quanto custa o dinheiro: o WACC
B13: Um real daqui a cinco anos vale menos que um real hoje. A taxa que faz essa conta é o WACC: a média entre o retorno que o acionista exige (Ke, pelo CAPM) e o juro da dívida depois do imposto.
B14: Juro sem risco | C14: =WACC!D5 -> 0.1291
B15: + Beta × prêmio de risco de mercado | C15: =WACC!D6*WACC!D7 -> 0.03197034
B16: (=) Ke, o retorno que o acionista exige | C16: =WACC!D9 -> 0.16107034
B17: Custo da dívida depois do imposto | C17: =WACC!D14 -> 0.04719
B18: Peso da dívida | C18: =WACC!D17 -> 0.2625
B19: WACC pelo CAPM (média de Ke e do custo da dívida) | C19: =WACC!D19 -> 0.13117675
B20: (=) WACC em uso (o do cenário ou do ajuste manual) | C20: =WACC!D22 -> 0.13117675 | D20: é a taxa de desconto
B22: 3. Trazer cada fluxo a valor de hoje
B23: Cada FCFF projetado é dividido por (1 + WACC) elevado ao número de anos até ele chegar. De 2026 só entra a parte do ano que ainda não aconteceu.
B24: FCFF de 2027E | C24: ='Valor justo'!E6 -> 27056.553
B25: × Fator de desconto | C25: ='Valor justo'!E10 -> 0.88358746 | D25: 1 ÷ (1 + WACC) elevado aos anos até lá
B26: (=) Valor presente do FCFF de 2027E | C26: ='Valor justo'!E11 -> 23906.831
B27: (=) Soma dos valores presentes de 2026 a 2030 | C27: ='Valor justo'!D21 -> 105265.59
B29: 4. O que vem depois de 2030: a perpetuidade
B30: A empresa não acaba em 2030. Supõe-se que o caixa cresce para sempre a uma taxa g, igual à inflação. A fórmula de Gordon resume todos esses anos em um número, o valor terminal.
B31: FCFF de 2030 ajustado (só repõe o que desgasta) | C31: ='Valor justo'!D16 -> 52965.919
B32: Crescimento para sempre (g) | C32: ='Valor justo'!D15 -> 0.035 | D32: inflação de longo prazo
B33: Valor terminal: FCFF × (1 + g) ÷ (WACC − g) | C33: ='Valor justo'!D17 -> 569989.38
B34: (=) Valor terminal a valor de hoje | C34: ='Valor justo'!D18 -> 327159.59
B36: 5. Valor da empresa (Enterprise Value)
B37: Somando os fluxos descontados e o valor terminal descontado chega-se ao valor da operação inteira, que pertence a credores e acionistas.
B38: Valor presente dos fluxos projetados | C38: ='Valor justo'!D21 -> 105265.59
B39: + Valor presente do valor terminal | C39: ='Valor justo'!D18 -> 327159.59
B40: (=) Valor da empresa (EV) | C40: ='Valor justo'!D22 -> 432425.19
B42: 6. Do valor da empresa ao valor do acionista (Equity Value)
B43: Tira-se o que é dos credores (dívida líquida) e dos sócios das controladas (minoritários) e soma-se o que a empresa tem em participações.
B44: Valor da empresa (EV) | C44: ='Valor justo'!D22 -> 432425.19
B45: − Dívida líquida | C45: ='Valor justo'!D23 -> 68192 | D45: é dos credores
B46: − Minoritários | C46: ='Valor justo'!D24 -> 4832 | D46: é dos sócios das controladas
B47: + Investimentos em coligadas | C47: ='Valor justo'!D25 -> 27248 | D47: o FCFF não contou
B48: (=) Valor do acionista (Equity Value) | C48: ='Valor justo'!D27 -> 386649.19
B50: 7. Preço justo por ação
B51: O valor do acionista dividido pelo número de ações dá o preço justo, que se compara com o preço na bolsa.
B52: Valor do acionista | C52: ='Valor justo'!D27 -> 386649.19
B53: ÷ Ações em circulação (milhões) | C53: ='Valor justo'!D28 -> 4072.366
B54: (=) Preço justo por ação | C54: ='Valor justo'!D29 -> 94.944606
B55: Preço de mercado | C55: ='Valor justo'!D30 -> 67.64
B56: Diferença | C56: ='Valor justo'!D31 -> 0.40367543 | D56: preço justo ÷ preço de mercado − 1

Sheet Demonstrativos
B1: ="Demonstrativos - "&Painel!$D$5 -> Demonstrativos - Vale (VALE3)
B2: DRE, fluxo de caixa e balanço da empresa escolhida no Painel, e os indicadores que saem deles. LTM = últimos doze meses; o balanço dessa coluna é o do trimestre.
B4: R$ milhões | C4: 2018 | D4: 2019 | E4: 2020 | F4: 2021 | G4: 2022 | H4: 2023 | I4: 2024 | J4: 2025 | K4: LTM 2T26 | L4: O que é
B5: Demonstração do resultado
B6: Receita líquida | C6: =INDEX(Dados!C$1:C$112,6+36*(Painel!$Y$5-1)) -> 134483.13 | D6: =INDEX(Dados!D$1:D$112,6+36*(Painel!$Y$5-1)) -> 148639.92 | E6: =INDEX(Dados!E$1:E$112,6+36*(Painel!$Y$5-1)) -> 208528.76 | F6: =INDEX(Dados!F$1:F$112,6+36*(Painel!$Y$5-1)) -> 293524 | G6: =INDEX(Dados!G$1:G$112,6+36*(Painel!$Y$5-1)) -> 226508 | H6: =INDEX(Dados!H$1:H$112,6+36*(Painel!$Y$5-1)) -> 208066 | I6: =INDEX(Dados!I$1:I$112,6+36*(Painel!$Y$5-1)) -> 206005 | J6: =INDEX(Dados!J$1:J$112,6+36*(Painel!$Y$5-1)) -> 213595 | K6: =INDEX(Dados!K$1:K$112,6+36*(Painel!$Y$5-1)) -> 218069 | L6: Tudo o que a empresa vendeu no período, já sem impostos sobre a venda.
B7: Custo dos produtos vendidos | C7: =INDEX(Dados!C$1:C$112,7+36*(Painel!$Y$5-1)) -> -81200.904 | D7: =INDEX(Dados!D$1:D$112,7+36*(Painel!$Y$5-1)) -> -83835.563 | E7: =INDEX(Dados!E$1:E$112,7+36*(Painel!$Y$5-1)) -> -98567.494 | F7: =INDEX(Dados!F$1:F$112,7+36*(Painel!$Y$5-1)) -> -117267 | G7: =INDEX(Dados!G$1:G$112,7+36*(Painel!$Y$5-1)) -> -124195 | H7: =INDEX(Dados!H$1:H$112,7+36*(Painel!$Y$5-1)) -> -120016 | I7: =INDEX(Dados!I$1:I$112,7+36*(Painel!$Y$5-1)) -> -131318 | J7: =INDEX(Dados!J$1:J$112,7+36*(Painel!$Y$5-1)) -> -138887 | K7: =INDEX(Dados!K$1:K$112,7+36*(Painel!$Y$5-1)) -> -141911 | L7: O que custou produzir o que foi vendido, incluindo a depreciação das fábricas e minas.
B8: Lucro bruto | C8: =INDEX(Dados!C$1:C$112,8+36*(Painel!$Y$5-1)) -> 53282.222 | D8: =INDEX(Dados!D$1:D$112,8+36*(Painel!$Y$5-1)) -> 64804.358 | E8: =INDEX(Dados!E$1:E$112,8+36*(Painel!$Y$5-1)) -> 109961.26 | F8: =INDEX(Dados!F$1:F$112,8+36*(Painel!$Y$5-1)) -> 176257 | G8: =INDEX(Dados!G$1:G$112,8+36*(Painel!$Y$5-1)) -> 102313 | H8: =INDEX(Dados!H$1:H$112,8+36*(Painel!$Y$5-1)) -> 88050 | I8: =INDEX(Dados!I$1:I$112,8+36*(Painel!$Y$5-1)) -> 74687 | J8: =INDEX(Dados!J$1:J$112,8+36*(Painel!$Y$5-1)) -> 74708 | K8: =INDEX(Dados!K$1:K$112,8+36*(Painel!$Y$5-1)) -> 76158 | L8: Receita menos custo dos produtos. O que sobra antes das despesas da empresa.
B9: Despesas com vendas | C9: =INDEX(Dados!C$1:C$112,9+36*(Painel!$Y$5-1)) -> 0 | D9: =INDEX(Dados!D$1:D$112,9+36*(Painel!$Y$5-1)) -> 0 | E9: =INDEX(Dados!E$1:E$112,9+36*(Painel!$Y$5-1)) -> 0 | F9: =INDEX(Dados!F$1:F$112,9+36*(Painel!$Y$5-1)) -> 0 | G9: =INDEX(Dados!G$1:G$112,9+36*(Painel!$Y$5-1)) -> 0 | H9: =INDEX(Dados!H$1:H$112,9+36*(Painel!$Y$5-1)) -> 0 | I9: =INDEX(Dados!I$1:I$112,9+36*(Painel!$Y$5-1)) -> 0 | J9: =INDEX(Dados!J$1:J$112,9+36*(Painel!$Y$5-1)) -> 0 | K9: =INDEX(Dados!K$1:K$112,9+36*(Painel!$Y$5-1)) -> 0 | L9: Gastos para vender e entregar: frete, comissões, equipe comercial.
B10: Despesas gerais e administrativas | C10: =INDEX(Dados!C$1:C$112,10+36*(Painel!$Y$5-1)) -> -1916.765 | D10: =INDEX(Dados!D$1:D$112,10+36*(Painel!$Y$5-1)) -> -1924.308 | E10: =INDEX(Dados!E$1:E$112,10+36*(Painel!$Y$5-1)) -> -2856.913 | F10: =INDEX(Dados!F$1:F$112,10+36*(Painel!$Y$5-1)) -> -2601 | G10: =INDEX(Dados!G$1:G$112,10+36*(Painel!$Y$5-1)) -> -2658 | H10: =INDEX(Dados!H$1:H$112,10+36*(Painel!$Y$5-1)) -> -2758 | I10: =INDEX(Dados!I$1:I$112,10+36*(Painel!$Y$5-1)) -> -3397 | J10: =INDEX(Dados!J$1:J$112,10+36*(Painel!$Y$5-1)) -> -3566 | K10: =INDEX(Dados!K$1:K$112,10+36*(Painel!$Y$5-1)) -> -3667 | L10: Gastos da administração: salários do escritório, sistemas, serviços.
B11: Perdas por recuperabilidade de ativos (impairment) | C11: =INDEX(Dados!C$1:C$112,11+36*(Painel!$Y$5-1)) -> -3523.458 | D11: =INDEX(Dados!D$1:D$112,11+36*(Painel!$Y$5-1)) -> -20762.371 | E11: =INDEX(Dados!E$1:E$112,11+36*(Painel!$Y$5-1)) -> -11818.792 | F11: =INDEX(Dados!F$1:F$112,11+36*(Painel!$Y$5-1)) -> -2352 | G11: =INDEX(Dados!G$1:G$112,11+36*(Painel!$Y$5-1)) -> 3833 | H11: =INDEX(Dados!H$1:H$112,11+36*(Painel!$Y$5-1)) -> -1317 | I11: =INDEX(Dados!I$1:I$112,11+36*(Painel!$Y$5-1)) -> 510 | J11: =INDEX(Dados!J$1:J$112,11+36*(Painel!$Y$5-1)) -> -25147 | K11: =INDEX(Dados!K$1:K$112,11+36*(Painel!$Y$5-1)) -> -23490 | L11: Baixa contábil de um ativo que passou a valer menos (impairment). Não sai do caixa.
B12: Total de despesas/receitas operacionais | C12: =INDEX(Dados!C$1:C$112,12+36*(Painel!$Y$5-1)) -> -10106.478 | D12: =INDEX(Dados!D$1:D$112,12+36*(Painel!$Y$5-1)) -> -62564.583 | E12: =INDEX(Dados!E$1:E$112,12+36*(Painel!$Y$5-1)) -> -57893.647 | F12: =INDEX(Dados!F$1:F$112,12+36*(Painel!$Y$5-1)) -> -34922 | G12: =INDEX(Dados!G$1:G$112,12+36*(Painel!$Y$5-1)) -> -11987 | H12: =INDEX(Dados!H$1:H$112,12+36*(Painel!$Y$5-1)) -> -22778 | I12: =INDEX(Dados!I$1:I$112,12+36*(Painel!$Y$5-1)) -> -19228 | J12: =INDEX(Dados!J$1:J$112,12+36*(Painel!$Y$5-1)) -> -42739 | K12: =INDEX(Dados!K$1:K$112,12+36*(Painel!$Y$5-1)) -> -42048 | L12: Soma de todas as despesas e receitas operacionais abaixo do lucro bruto.
B13: Equivalência patrimonial | C13: =INDEX(Dados!C$1:C$112,13+36*(Painel!$Y$5-1)) -> -693.486 | D13: =INDEX(Dados!D$1:D$112,13+36*(Painel!$Y$5-1)) -> -2683.903 | E13: =INDEX(Dados!E$1:E$112,13+36*(Painel!$Y$5-1)) -> -5435.93 | F13: =INDEX(Dados!F$1:F$112,13+36*(Painel!$Y$5-1)) -> -6947 | G13: =INDEX(Dados!G$1:G$112,13+36*(Painel!$Y$5-1)) -> 1616 | H13: =INDEX(Dados!H$1:H$112,13+36*(Painel!$Y$5-1)) -> -5434 | I13: =INDEX(Dados!I$1:I$112,13+36*(Painel!$Y$5-1)) -> -1570 | J13: =INDEX(Dados!J$1:J$112,13+36*(Painel!$Y$5-1)) -> -1170 | K13: =INDEX(Dados!K$1:K$112,13+36*(Painel!$Y$5-1)) -> -453 | L13: Parte do lucro de empresas das quais ela é sócia sem controlar. Não entra no caixa.
B14: EBIT (resultado antes do financeiro e dos tributos) | C14: =INDEX(Dados!C$1:C$112,14+36*(Painel!$Y$5-1)) -> 43175.744 | D14: =INDEX(Dados!D$1:D$112,14+36*(Painel!$Y$5-1)) -> 2239.775 | E14: =INDEX(Dados!E$1:E$112,14+36*(Painel!$Y$5-1)) -> 52067.618 | F14: =INDEX(Dados!F$1:F$112,14+36*(Painel!$Y$5-1)) -> 141335 | G14: =INDEX(Dados!G$1:G$112,14+36*(Painel!$Y$5-1)) -> 90326 | H14: =INDEX(Dados!H$1:H$112,14+36*(Painel!$Y$5-1)) -> 65272 | I14: =INDEX(Dados!I$1:I$112,14+36*(Painel!$Y$5-1)) -> 55459 | J14: =INDEX(Dados!J$1:J$112,14+36*(Painel!$Y$5-1)) -> 31969 | K14: =INDEX(Dados!K$1:K$112,14+36*(Painel!$Y$5-1)) -> 34110 | L14: Lucro da operação, antes de juros e imposto de renda. Lucro bruto menos despesas.
B15: Resultado financeiro | C15: =INDEX(Dados!C$1:C$112,15+36*(Painel!$Y$5-1)) -> -18057.519 | D15: =INDEX(Dados!D$1:D$112,15+36*(Painel!$Y$5-1)) -> -13444.786 | E15: =INDEX(Dados!E$1:E$112,15+36*(Painel!$Y$5-1)) -> -24140.63 | F15: =INDEX(Dados!F$1:F$112,15+36*(Painel!$Y$5-1)) -> 17812 | G15: =INDEX(Dados!G$1:G$112,15+36*(Painel!$Y$5-1)) -> 11378 | H15: =INDEX(Dados!H$1:H$112,15+36*(Painel!$Y$5-1)) -> -9718 | I15: =INDEX(Dados!I$1:I$112,15+36*(Painel!$Y$5-1)) -> -21235 | J15: =INDEX(Dados!J$1:J$112,15+36*(Painel!$Y$5-1)) -> -5276 | K15: =INDEX(Dados!K$1:K$112,15+36*(Painel!$Y$5-1)) -> -9699 | L15: Juros recebidos menos juros pagos, mais variação cambial e derivativos.
B16: Lucro antes dos tributos | C16: =INDEX(Dados!C$1:C$112,16+36*(Painel!$Y$5-1)) -> 25118.225 | D16: =INDEX(Dados!D$1:D$112,16+36*(Painel!$Y$5-1)) -> -11205.011 | E16: =INDEX(Dados!E$1:E$112,16+36*(Painel!$Y$5-1)) -> 27926.988 | F16: =INDEX(Dados!F$1:F$112,16+36*(Painel!$Y$5-1)) -> 159147 | G16: =INDEX(Dados!G$1:G$112,16+36*(Painel!$Y$5-1)) -> 101704 | H16: =INDEX(Dados!H$1:H$112,16+36*(Painel!$Y$5-1)) -> 55554 | I16: =INDEX(Dados!I$1:I$112,16+36*(Painel!$Y$5-1)) -> 34224 | J16: =INDEX(Dados!J$1:J$112,16+36*(Painel!$Y$5-1)) -> 26693 | K16: =INDEX(Dados!K$1:K$112,16+36*(Painel!$Y$5-1)) -> 24411 | L16: Lucro antes do imposto de renda: EBIT mais o resultado financeiro.
B17: Imposto de renda e CSLL | C17: =INDEX(Dados!C$1:C$112,17+36*(Painel!$Y$5-1)) -> 965.98 | D17: =INDEX(Dados!D$1:D$112,17+36*(Painel!$Y$5-1)) -> 2508.971 | E17: =INDEX(Dados!E$1:E$112,17+36*(Painel!$Y$5-1)) -> -3024.647 | F17: =INDEX(Dados!F$1:F$112,17+36*(Painel!$Y$5-1)) -> -25320 | G17: =INDEX(Dados!G$1:G$112,17+36*(Painel!$Y$5-1)) -> -15185 | H17: =INDEX(Dados!H$1:H$112,17+36*(Painel!$Y$5-1)) -> -15000 | I17: =INDEX(Dados!I$1:I$112,17+36*(Painel!$Y$5-1)) -> -3793 | J17: =INDEX(Dados!J$1:J$112,17+36*(Painel!$Y$5-1)) -> -14882 | K17: =INDEX(Dados!K$1:K$112,17+36*(Painel!$Y$5-1)) -> -15720 | L17: Imposto de renda e contribuição social sobre o lucro.
B18: Lucro líquido consolidado | C18: =INDEX(Dados!C$1:C$112,18+36*(Painel!$Y$5-1)) -> 25773.768 | D18: =INDEX(Dados!D$1:D$112,18+36*(Painel!$Y$5-1)) -> -8696.04 | E18: =INDEX(Dados!E$1:E$112,18+36*(Painel!$Y$5-1)) -> 24902.341 | F18: =INDEX(Dados!F$1:F$112,18+36*(Painel!$Y$5-1)) -> 121343 | G18: =INDEX(Dados!G$1:G$112,18+36*(Painel!$Y$5-1)) -> 96337 | H18: =INDEX(Dados!H$1:H$112,18+36*(Painel!$Y$5-1)) -> 40554 | I18: =INDEX(Dados!I$1:I$112,18+36*(Painel!$Y$5-1)) -> 30431 | J18: =INDEX(Dados!J$1:J$112,18+36*(Painel!$Y$5-1)) -> 11811 | K18: =INDEX(Dados!K$1:K$112,18+36*(Painel!$Y$5-1)) -> 8691 | L18: O que sobra para os sócios depois de tudo: custos, despesas, juros e impostos.
B19: Lucro atribuído aos controladores | C19: =INDEX(Dados!C$1:C$112,19+36*(Painel!$Y$5-1)) -> 25656.526 | D19: =INDEX(Dados!D$1:D$112,19+36*(Painel!$Y$5-1)) -> -6671.445 | E19: =INDEX(Dados!E$1:E$112,19+36*(Painel!$Y$5-1)) -> 26712.713 | F19: =INDEX(Dados!F$1:F$112,19+36*(Painel!$Y$5-1)) -> 121228 | G19: =INDEX(Dados!G$1:G$112,19+36*(Painel!$Y$5-1)) -> 95924 | H19: =INDEX(Dados!H$1:H$112,19+36*(Painel!$Y$5-1)) -> 39940 | I19: =INDEX(Dados!I$1:I$112,19+36*(Painel!$Y$5-1)) -> 31592 | J19: =INDEX(Dados!J$1:J$112,19+36*(Painel!$Y$5-1)) -> 13814 | K19: =INDEX(Dados!K$1:K$112,19+36*(Painel!$Y$5-1)) -> 10369 | L19: A parte do lucro que pertence aos acionistas da empresa, sem os sócios de controladas.
B20: Fluxo de caixa
B21: Depreciação, amortização e exaustão | C21: =INDEX(Dados!C$1:C$112,20+36*(Painel!$Y$5-1)) -> 12238.935 | D21: =INDEX(Dados!D$1:D$112,20+36*(Painel!$Y$5-1)) -> 14750.733 | E21: =INDEX(Dados!E$1:E$112,20+36*(Painel!$Y$5-1)) -> 16679.216 | F21: =INDEX(Dados!F$1:F$112,20+36*(Painel!$Y$5-1)) -> 16379 | G21: =INDEX(Dados!G$1:G$112,20+36*(Painel!$Y$5-1)) -> 16386 | H21: =INDEX(Dados!H$1:H$112,20+36*(Painel!$Y$5-1)) -> 15300 | I21: =INDEX(Dados!I$1:I$112,20+36*(Painel!$Y$5-1)) -> 16525 | J21: =INDEX(Dados!J$1:J$112,20+36*(Painel!$Y$5-1)) -> 17306 | K21: =INDEX(Dados!K$1:K$112,20+36*(Painel!$Y$5-1)) -> 17823 | L21: Desgaste contábil de máquinas, minas e prédios no período. É custo, mas não sai do caixa.
B22: Caixa das atividades operacionais | C22: =INDEX(Dados!C$1:C$112,21+36*(Painel!$Y$5-1)) -> 47930.771 | D22: =INDEX(Dados!D$1:D$112,21+36*(Painel!$Y$5-1)) -> 47283.755 | E22: =INDEX(Dados!E$1:E$112,21+36*(Painel!$Y$5-1)) -> 75207.873 | F22: =INDEX(Dados!F$1:F$112,21+36*(Painel!$Y$5-1)) -> 136766 | G22: =INDEX(Dados!G$1:G$112,21+36*(Painel!$Y$5-1)) -> 58201 | H22: =INDEX(Dados!H$1:H$112,21+36*(Painel!$Y$5-1)) -> 65905 | I22: =INDEX(Dados!I$1:I$112,21+36*(Painel!$Y$5-1)) -> 50199 | J22: =INDEX(Dados!J$1:J$112,21+36*(Painel!$Y$5-1)) -> 48765 | K22: =INDEX(Dados!K$1:K$112,21+36*(Painel!$Y$5-1)) -> 50599 | L22: Dinheiro que a operação gerou de verdade no período, depois de impostos e capital de giro.
B23: Investimento em imobilizado e intangível (capex) | C23: =INDEX(Dados!C$1:C$112,22+36*(Painel!$Y$5-1)) -> 13978.533 | D23: =INDEX(Dados!D$1:D$112,22+36*(Painel!$Y$5-1)) -> 14773.97 | E23: =INDEX(Dados!E$1:E$112,22+36*(Painel!$Y$5-1)) -> 22725.636 | F23: =INDEX(Dados!F$1:F$112,22+36*(Painel!$Y$5-1)) -> 27301 | G23: =INDEX(Dados!G$1:G$112,22+36*(Painel!$Y$5-1)) -> 28184 | H23: =INDEX(Dados!H$1:H$112,22+36*(Painel!$Y$5-1)) -> 29446 | I23: =INDEX(Dados!I$1:I$112,22+36*(Painel!$Y$5-1)) -> 35098 | J23: =INDEX(Dados!J$1:J$112,22+36*(Painel!$Y$5-1)) -> 33390 | K23: =INDEX(Dados!K$1:K$112,22+36*(Painel!$Y$5-1)) -> 31848 | L23: Dinheiro investido em máquinas, minas, fábricas e sistemas.
B24: Dividendos e JCP pagos | C24: =INDEX(Dados!C$1:C$112,23+36*(Painel!$Y$5-1)) -> 13050.573 | D24: =INDEX(Dados!D$1:D$112,23+36*(Painel!$Y$5-1)) -> 695.071 | E24: =INDEX(Dados!E$1:E$112,23+36*(Painel!$Y$5-1)) -> 18708.953 | F24: =INDEX(Dados!F$1:F$112,23+36*(Painel!$Y$5-1)) -> 73287 | G24: =INDEX(Dados!G$1:G$112,23+36*(Painel!$Y$5-1)) -> 34157 | H24: =INDEX(Dados!H$1:H$112,23+36*(Painel!$Y$5-1)) -> 27967 | I24: =INDEX(Dados!I$1:I$112,23+36*(Painel!$Y$5-1)) -> 20663 | J24: =INDEX(Dados!J$1:J$112,23+36*(Painel!$Y$5-1)) -> 19971 | K24: =INDEX(Dados!K$1:K$112,23+36*(Painel!$Y$5-1)) -> 23071 | L24: Dinheiro entregue aos acionistas como dividendos e juros sobre capital próprio.
B25: Balanço patrimonial
B26: Caixa e equivalentes | C26: =INDEX(Dados!C$1:C$112,24+36*(Painel!$Y$5-1)) -> 22412.547 | D26: =INDEX(Dados!D$1:D$112,24+36*(Painel!$Y$5-1)) -> 29627.092 | E26: =INDEX(Dados!E$1:E$112,24+36*(Painel!$Y$5-1)) -> 70085.566 | F26: =INDEX(Dados!F$1:F$112,24+36*(Painel!$Y$5-1)) -> 65409 | G26: =INDEX(Dados!G$1:G$112,24+36*(Painel!$Y$5-1)) -> 24711 | H26: =INDEX(Dados!H$1:H$112,24+36*(Painel!$Y$5-1)) -> 17474 | I26: =INDEX(Dados!I$1:I$112,24+36*(Painel!$Y$5-1)) -> 30671 | J26: =INDEX(Dados!J$1:J$112,24+36*(Painel!$Y$5-1)) -> 40563 | K26: =INDEX(Dados!K$1:K$112,24+36*(Painel!$Y$5-1)) -> 28871 | L26: Dinheiro em conta e aplicações de resgate imediato.
B27: Aplicações financeiras | C27: =INDEX(Dados!C$1:C$112,25+36*(Painel!$Y$5-1)) -> 0 | D27: =INDEX(Dados!D$1:D$112,25+36*(Painel!$Y$5-1)) -> 0 | E27: =INDEX(Dados!E$1:E$112,25+36*(Painel!$Y$5-1)) -> 0 | F27: =INDEX(Dados!F$1:F$112,25+36*(Painel!$Y$5-1)) -> 1028 | G27: =INDEX(Dados!G$1:G$112,25+36*(Painel!$Y$5-1)) -> 320 | H27: =INDEX(Dados!H$1:H$112,25+36*(Painel!$Y$5-1)) -> 250 | I27: =INDEX(Dados!I$1:I$112,25+36*(Painel!$Y$5-1)) -> 331 | J27: =INDEX(Dados!J$1:J$112,25+36*(Painel!$Y$5-1)) -> 1066 | K27: =INDEX(Dados!K$1:K$112,25+36*(Painel!$Y$5-1)) -> 971 | L27: Aplicações financeiras de curto prazo.
B28: Contas a receber | C28: =INDEX(Dados!C$1:C$112,26+36*(Painel!$Y$5-1)) -> 11669.973 | D28: =INDEX(Dados!D$1:D$112,26+36*(Painel!$Y$5-1)) -> 11483.278 | E28: =INDEX(Dados!E$1:E$112,26+36*(Painel!$Y$5-1)) -> 27233.885 | F28: =INDEX(Dados!F$1:F$112,26+36*(Painel!$Y$5-1)) -> 21840 | G28: =INDEX(Dados!G$1:G$112,26+36*(Painel!$Y$5-1)) -> 22537 | H28: =INDEX(Dados!H$1:H$112,26+36*(Painel!$Y$5-1)) -> 20317 | I28: =INDEX(Dados!I$1:I$112,26+36*(Painel!$Y$5-1)) -> 14600 | J28: =INDEX(Dados!J$1:J$112,26+36*(Painel!$Y$5-1)) -> 12639 | K28: =INDEX(Dados!K$1:K$112,26+36*(Painel!$Y$5-1)) -> 13534 | L28: Vendas já feitas que os clientes ainda não pagaram.
B29: Estoques | C29: =INDEX(Dados!C$1:C$112,27+36*(Painel!$Y$5-1)) -> 17215.947 | D29: =INDEX(Dados!D$1:D$112,27+36*(Painel!$Y$5-1)) -> 17228.428 | E29: =INDEX(Dados!E$1:E$112,27+36*(Painel!$Y$5-1)) -> 21102.768 | F29: =INDEX(Dados!F$1:F$112,27+36*(Painel!$Y$5-1)) -> 24429 | G29: =INDEX(Dados!G$1:G$112,27+36*(Painel!$Y$5-1)) -> 23386 | H29: =INDEX(Dados!H$1:H$112,27+36*(Painel!$Y$5-1)) -> 22679 | I29: =INDEX(Dados!I$1:I$112,27+36*(Painel!$Y$5-1)) -> 28513 | J29: =INDEX(Dados!J$1:J$112,27+36*(Painel!$Y$5-1)) -> 32666 | K29: =INDEX(Dados!K$1:K$112,27+36*(Painel!$Y$5-1)) -> 32424 | L29: Matéria-prima e produto pronto que ainda não foi vendido.
B30: Ativo circulante | C30: =INDEX(Dados!C$1:C$112,28+36*(Painel!$Y$5-1)) -> 59256.115 | D30: =INDEX(Dados!D$1:D$112,28+36*(Painel!$Y$5-1)) -> 68697.547 | E30: =INDEX(Dados!E$1:E$112,28+36*(Painel!$Y$5-1)) -> 126805.17 | F30: =INDEX(Dados!F$1:F$112,28+36*(Painel!$Y$5-1)) -> 124800 | G30: =INDEX(Dados!G$1:G$112,28+36*(Painel!$Y$5-1)) -> 81009 | H30: =INDEX(Dados!H$1:H$112,28+36*(Painel!$Y$5-1)) -> 90529 | I30: =INDEX(Dados!I$1:I$112,28+36*(Painel!$Y$5-1)) -> 83476 | J30: =INDEX(Dados!J$1:J$112,28+36*(Painel!$Y$5-1)) -> 100645 | K30: =INDEX(Dados!K$1:K$112,28+36*(Painel!$Y$5-1)) -> 91411 | L30: Tudo o que vira dinheiro em até um ano.
B31: Investimentos em coligadas | C31: =INDEX(Dados!C$1:C$112,29+36*(Painel!$Y$5-1)) -> 12495.002 | D31: =INDEX(Dados!D$1:D$112,29+36*(Painel!$Y$5-1)) -> 11277.871 | E31: =INDEX(Dados!E$1:E$112,29+36*(Painel!$Y$5-1)) -> 10556.64 | F31: =INDEX(Dados!F$1:F$112,29+36*(Painel!$Y$5-1)) -> 9771 | G31: =INDEX(Dados!G$1:G$112,29+36*(Painel!$Y$5-1)) -> 9381 | H31: =INDEX(Dados!H$1:H$112,29+36*(Painel!$Y$5-1)) -> 9061 | I31: =INDEX(Dados!I$1:I$112,29+36*(Painel!$Y$5-1)) -> 28158 | J31: =INDEX(Dados!J$1:J$112,29+36*(Painel!$Y$5-1)) -> 27674 | K31: =INDEX(Dados!K$1:K$112,29+36*(Painel!$Y$5-1)) -> 27248 | L31: Participação em outras empresas, pelo valor registrado no balanço.
B32: Imobilizado | C32: =INDEX(Dados!C$1:C$112,30+36*(Painel!$Y$5-1)) -> 187481.5 | D32: =INDEX(Dados!D$1:D$112,30+36*(Painel!$Y$5-1)) -> 187733.15 | E32: =INDEX(Dados!E$1:E$112,30+36*(Painel!$Y$5-1)) -> 213835.75 | F32: =INDEX(Dados!F$1:F$112,30+36*(Painel!$Y$5-1)) -> 233995 | G32: =INDEX(Dados!G$1:G$112,30+36*(Painel!$Y$5-1)) -> 234472 | H32: =INDEX(Dados!H$1:H$112,30+36*(Painel!$Y$5-1)) -> 234302 | I32: =INDEX(Dados!I$1:I$112,30+36*(Painel!$Y$5-1)) -> 247594 | J32: =INDEX(Dados!J$1:J$112,30+36*(Painel!$Y$5-1)) -> 240040 | K32: =INDEX(Dados!K$1:K$112,30+36*(Painel!$Y$5-1)) -> 240188 | L32: Máquinas, minas, fábricas e terrenos, já descontada a depreciação.
B33: Intangível | C33: =INDEX(Dados!C$1:C$112,31+36*(Painel!$Y$5-1)) -> 30850.392 | D33: =INDEX(Dados!D$1:D$112,31+36*(Painel!$Y$5-1)) -> 34256.976 | E33: =INDEX(Dados!E$1:E$112,31+36*(Painel!$Y$5-1)) -> 48308.512 | F33: =INDEX(Dados!F$1:F$112,31+36*(Painel!$Y$5-1)) -> 50287 | G33: =INDEX(Dados!G$1:G$112,31+36*(Painel!$Y$5-1)) -> 53421 | H33: =INDEX(Dados!H$1:H$112,31+36*(Painel!$Y$5-1)) -> 56309 | I33: =INDEX(Dados!I$1:I$112,31+36*(Painel!$Y$5-1)) -> 65105 | J33: =INDEX(Dados!J$1:J$112,31+36*(Painel!$Y$5-1)) -> 49261 | K33: =INDEX(Dados!K$1:K$112,31+36*(Painel!$Y$5-1)) -> 48775 | L33: Direitos, licenças, softwares e ágio de aquisições.
B34: Ativo total | C34: =INDEX(Dados!C$1:C$112,32+36*(Painel!$Y$5-1)) -> 341714.84 | D34: =INDEX(Dados!D$1:D$112,32+36*(Painel!$Y$5-1)) -> 369670.33 | E34: =INDEX(Dados!E$1:E$112,32+36*(Painel!$Y$5-1)) -> 478129.52 | F34: =INDEX(Dados!F$1:F$112,32+36*(Painel!$Y$5-1)) -> 499128 | G34: =INDEX(Dados!G$1:G$112,32+36*(Painel!$Y$5-1)) -> 453387 | H34: =INDEX(Dados!H$1:H$112,32+36*(Painel!$Y$5-1)) -> 455984 | I34: =INDEX(Dados!I$1:I$112,32+36*(Painel!$Y$5-1)) -> 496325 | J34: =INDEX(Dados!J$1:J$112,32+36*(Painel!$Y$5-1)) -> 476094 | K34: =INDEX(Dados!K$1:K$112,32+36*(Painel!$Y$5-1)) -> 462161 | L34: Tudo o que a empresa tem.
B35: Fornecedores | C35: =INDEX(Dados!C$1:C$112,33+36*(Painel!$Y$5-1)) -> 13609.716 | D35: =INDEX(Dados!D$1:D$112,33+36*(Painel!$Y$5-1)) -> 16555.739 | E35: =INDEX(Dados!E$1:E$112,33+36*(Painel!$Y$5-1)) -> 17495.96 | F35: =INDEX(Dados!F$1:F$112,33+36*(Painel!$Y$5-1)) -> 19393 | G35: =INDEX(Dados!G$1:G$112,33+36*(Painel!$Y$5-1)) -> 23278 | H35: =INDEX(Dados!H$1:H$112,33+36*(Painel!$Y$5-1)) -> 25523 | I35: =INDEX(Dados!I$1:I$112,33+36*(Painel!$Y$5-1)) -> 26217 | J35: =INDEX(Dados!J$1:J$112,33+36*(Painel!$Y$5-1)) -> 30621 | K35: =INDEX(Dados!K$1:K$112,33+36*(Painel!$Y$5-1)) -> 32113 | L35: Compras já recebidas que a empresa ainda não pagou.
B36: Empréstimos e financiamentos - curto prazo | C36: =INDEX(Dados!C$1:C$112,34+36*(Painel!$Y$5-1)) -> 3888.522 | D36: =INDEX(Dados!D$1:D$112,34+36*(Painel!$Y$5-1)) -> 5804.801 | E36: =INDEX(Dados!E$1:E$112,34+36*(Painel!$Y$5-1)) -> 5901.375 | F36: =INDEX(Dados!F$1:F$112,34+36*(Painel!$Y$5-1)) -> 6720 | G36: =INDEX(Dados!G$1:G$112,34+36*(Painel!$Y$5-1)) -> 2552 | H36: =INDEX(Dados!H$1:H$112,34+36*(Painel!$Y$5-1)) -> 4940 | I36: =INDEX(Dados!I$1:I$112,34+36*(Painel!$Y$5-1)) -> 7223 | J36: =INDEX(Dados!J$1:J$112,34+36*(Painel!$Y$5-1)) -> 3731 | K36: =INDEX(Dados!K$1:K$112,34+36*(Painel!$Y$5-1)) -> 6534 | L36: Empréstimos e financiamentos que vencem em até um ano.
B37: Passivo circulante | C37: =INDEX(Dados!C$1:C$112,35+36*(Painel!$Y$5-1)) -> 35516.662 | D37: =INDEX(Dados!D$1:D$112,35+36*(Painel!$Y$5-1)) -> 55805.644 | E37: =INDEX(Dados!E$1:E$112,35+36*(Painel!$Y$5-1)) -> 75837.515 | F37: =INDEX(Dados!F$1:F$112,35+36*(Painel!$Y$5-1)) -> 84814 | G37: =INDEX(Dados!G$1:G$112,35+36*(Painel!$Y$5-1)) -> 72478 | H37: =INDEX(Dados!H$1:H$112,35+36*(Painel!$Y$5-1)) -> 70948 | I37: =INDEX(Dados!I$1:I$112,35+36*(Painel!$Y$5-1)) -> 81055 | J37: =INDEX(Dados!J$1:J$112,35+36*(Painel!$Y$5-1)) -> 87320 | K37: =INDEX(Dados!K$1:K$112,35+36*(Painel!$Y$5-1)) -> 76703 | L37: Tudo o que a empresa tem de pagar em até um ano.
B38: Empréstimos e financiamentos - longo prazo | C38: =INDEX(Dados!C$1:C$112,36+36*(Painel!$Y$5-1)) -> 56039.432 | D38: =INDEX(Dados!D$1:D$112,36+36*(Painel!$Y$5-1)) -> 54037.929 | E38: =INDEX(Dados!E$1:E$112,36+36*(Painel!$Y$5-1)) -> 72187.72 | F38: =INDEX(Dados!F$1:F$112,36+36*(Painel!$Y$5-1)) -> 70189 | G38: =INDEX(Dados!G$1:G$112,36+36*(Painel!$Y$5-1)) -> 63778 | H38: =INDEX(Dados!H$1:H$112,36+36*(Painel!$Y$5-1)) -> 62464 | I38: =INDEX(Dados!I$1:I$112,36+36*(Painel!$Y$5-1)) -> 88789 | J38: =INDEX(Dados!J$1:J$112,36+36*(Painel!$Y$5-1)) -> 99726 | K38: =INDEX(Dados!K$1:K$112,36+36*(Painel!$Y$5-1)) -> 91500 | L38: Empréstimos e financiamentos que vencem depois de um ano.
B39: Patrimônio líquido consolidado | C39: =INDEX(Dados!C$1:C$112,37+36*(Painel!$Y$5-1)) -> 173682.18 | D39: =INDEX(Dados!D$1:D$112,37+36*(Painel!$Y$5-1)) -> 157149.35 | E39: =INDEX(Dados!E$1:E$112,37+36*(Painel!$Y$5-1)) -> 180985.98 | F39: =INDEX(Dados!F$1:F$112,37+36*(Painel!$Y$5-1)) -> 197058 | G39: =INDEX(Dados!G$1:G$112,37+36*(Painel!$Y$5-1)) -> 194894 | H39: =INDEX(Dados!H$1:H$112,37+36*(Painel!$Y$5-1)) -> 198325 | I39: =INDEX(Dados!I$1:I$112,37+36*(Painel!$Y$5-1)) -> 213720 | J39: =INDEX(Dados!J$1:J$112,37+36*(Painel!$Y$5-1)) -> 188926 | K39: =INDEX(Dados!K$1:K$112,37+36*(Painel!$Y$5-1)) -> 201467 | L39: O que é dos sócios: ativo total menos todas as dívidas e obrigações.
B40: Participação de não controladores | C40: =INDEX(Dados!C$1:C$112,38+36*(Painel!$Y$5-1)) -> 3279.552 | D40: =INDEX(Dados!D$1:D$112,38+36*(Painel!$Y$5-1)) -> -4330.947 | E40: =INDEX(Dados!E$1:E$112,38+36*(Painel!$Y$5-1)) -> -4798.995 | F40: =INDEX(Dados!F$1:F$112,38+36*(Painel!$Y$5-1)) -> 4655 | G40: =INDEX(Dados!G$1:G$112,38+36*(Painel!$Y$5-1)) -> 7782 | H40: =INDEX(Dados!H$1:H$112,38+36*(Painel!$Y$5-1)) -> 7360 | I40: =INDEX(Dados!I$1:I$112,38+36*(Painel!$Y$5-1)) -> 6948 | J40: =INDEX(Dados!J$1:J$112,38+36*(Painel!$Y$5-1)) -> 4627 | K40: =INDEX(Dados!K$1:K$112,38+36*(Painel!$Y$5-1)) -> 4832 | L40: A parte do patrimônio que pertence a sócios de empresas controladas.
B42: Indicadores (fórmulas) | C42: 2018 | D42: 2019 | E42: 2020 | F42: 2021 | G42: 2022 | H42: 2023 | I42: 2024 | J42: 2025 | K42: LTM 2T26 | L42: O que é e como se calcula
B43: EBITDA (EBIT + depreciação) | C43: =C14+C21 -> 55414.679 | D43: =D14+D21 -> 16990.508 | E43: =E14+E21 -> 68746.834 | F43: =F14+F21 -> 157714 | G43: =G14+G21 -> 106712 | H43: =H14+H21 -> 80572 | I43: =I14+I21 -> 71984 | J43: =J14+J21 -> 49275 | K43: =K14+K21 -> 51933 | L43: EBIT + depreciação. Aproxima o caixa que a operação gera antes de investir e pagar juros.
B44: EBITDA sem perdas por recuperabilidade | C44: =C43-C11 -> 58938.137 | D44: =D43-D11 -> 37752.879 | E44: =E43-E11 -> 80565.626 | F44: =F43-F11 -> 160066 | G44: =G43-G11 -> 102879 | H44: =H43-H11 -> 81889 | I44: =I43-I11 -> 71474 | J44: =J43-J11 -> 74422 | K44: =K43-K11 -> 75423 | L44: EBITDA sem as perdas por recuperabilidade, que não se repetem. É a base da projeção.
B45: Custo caixa (custo sem depreciação) | C45: =C7+C21 -> -68961.969 | D45: =D7+D21 -> -69084.83 | E45: =E7+E21 -> -81888.278 | F45: =F7+F21 -> -100888 | G45: =G7+G21 -> -107809 | H45: =H7+H21 -> -104716 | I45: =I7+I21 -> -114793 | J45: =J7+J21 -> -121581 | K45: =K7+K21 -> -124088 | L45: Custo dos produtos sem a depreciação: o custo que de fato sai do caixa.
B46: Outras receitas/despesas operacionais | C46: =C12-C9-C10-C13 -> -7496.227 | D46: =D12-D9-D10-D13 -> -57956.372 | E46: =E12-E9-E10-E13 -> -49600.804 | F46: =F12-F9-F10-F13 -> -25374 | G46: =G12-G9-G10-G13 -> -10945 | H46: =H12-H9-H10-H13 -> -14586 | I46: =I12-I9-I10-I13 -> -14261 | J46: =J12-J9-J10-J13 -> -38003 | K46: =K12-K9-K10-K13 -> -37928 | L46: Despesas operacionais que não são vendas nem administrativas: provisões, baixas, ganhos avulsos.
B47: NOPAT (lucro operacional após imposto de 34%) | C47: =(C14-C13)*(1-0.34) -> 28953.692 | D47: =(D14-D13)*(1-0.34) -> 3249.6275 | E47: =(E14-E13)*(1-0.34) -> 37952.342 | F47: =(F14-F13)*(1-0.34) -> 97866.12 | G47: =(G14-G13)*(1-0.34) -> 58548.6 | H47: =(H14-H13)*(1-0.34) -> 46665.96 | I47: =(I14-I13)*(1-0.34) -> 37639.14 | J47: =(J14-J13)*(1-0.34) -> 21871.74 | K47: =(K14-K13)*(1-0.34) -> 22811.58 | L47: Lucro da operação depois do imposto, como se a empresa não tivesse dívida. (EBIT − equivalência) × (1 − 34%).
B48: Crescimento da receita | D48: =D6/C6-1 -> 0.10526819 | E48: =E6/D6-1 -> 0.4029122 | F48: =F6/E6-1 -> 0.40759482 | G48: =G6/F6-1 -> -0.22831523 | H48: =H6/G6-1 -> -0.081418758 | I48: =I6/H6-1 -> -0.0099055108 | J48: =J6/I6-1 -> 0.036843766 | K48: =K6/J6-1 -> 0.020946183 | L48: Receita do período dividida pela do período anterior, menos 1.
B49: Margem bruta | C49: =C8/C6 -> 0.39620006 | D49: =D8/D6 -> 0.43598219 | E49: =E8/E6 -> 0.52731942 | F49: =F8/F6 -> 0.60048582 | G49: =G8/G6 -> 0.45169707 | H49: =H8/H6 -> 0.42318303 | I49: =I8/I6 -> 0.36254945 | J49: =J8/J6 -> 0.34976474 | K49: =K8/K6 -> 0.34923809 | L49: Lucro bruto dividido pela receita: quanto sobra de cada real vendido depois do custo.
B50: Margem EBITDA | C50: =C43/C6 -> 0.41205674 | D50: =D43/D6 -> 0.11430649 | E50: =E43/E6 -> 0.32967555 | F50: =F43/F6 -> 0.53731211 | G50: =G43/G6 -> 0.47111802 | H50: =H43/H6 -> 0.38724251 | I50: =I43/I6 -> 0.34942841 | J50: =J43/J6 -> 0.2306936 | K50: =K43/K6 -> 0.23814939 | L50: EBITDA dividido pela receita: quanto de cada real vendido vira caixa operacional.
B51: Margem EBITDA sem perdas por recuperabilidade | C51: =C44/C6 -> 0.43825674 | D51: =D44/D6 -> 0.25398883 | E51: =E44/E6 -> 0.38635259 | F51: =F44/F6 -> 0.54532508 | G51: =G44/G6 -> 0.45419588 | H51: =H44/H6 -> 0.39357223 | I51: =I44/I6 -> 0.34695274 | J51: =J44/J6 -> 0.34842576 | K51: =K44/K6 -> 0.34586759 | L51: EBITDA sem perdas por recuperabilidade dividido pela receita.
B52: Margem EBIT | C52: =C14/C6 -> 0.32104953 | D52: =D14/D6 -> 0.015068462 | E52: =E14/E6 -> 0.24969035 | F52: =F14/F6 -> 0.48151088 | G52: =G14/G6 -> 0.3987762 | H52: =H14/H6 -> 0.31370815 | I52: =I14/I6 -> 0.26921191 | J52: =J14/J6 -> 0.14967111 | K52: =K14/K6 -> 0.15641838 | L52: EBIT dividido pela receita.
B53: Margem líquida | C53: =C18/C6 -> 0.19165057 | D53: =D18/D6 -> -0.058504068 | E53: =E18/E6 -> 0.11941922 | F53: =F18/F6 -> 0.41340061 | G53: =G18/G6 -> 0.4253139 | H53: =H18/H6 -> 0.19490931 | I53: =I18/I6 -> 0.14771972 | J53: =J18/J6 -> 0.055296238 | K53: =K18/K6 -> 0.039854358 | L53: Lucro líquido dividido pela receita: quanto de cada real vendido sobra para o sócio.
B54: Capex / receita | C54: =C23/C6 -> 0.10394265 | D54: =D23/D6 -> 0.099394361 | E54: =E23/E6 -> 0.10898082 | F54: =F23/F6 -> 0.093011134 | G54: =G23/G6 -> 0.12442828 | H54: =H23/H6 -> 0.1415224 | I54: =I23/I6 -> 0.17037451 | J54: =J23/J6 -> 0.15632388 | K54: =K23/K6 -> 0.14604552 | L54: Capex dividido pela receita: quanto da venda é reinvestido.
B55: Ativo fixo (imobilizado + intangível) | C55: =C32+C33 -> 218331.89 | D55: =D32+D33 -> 221990.13 | E55: =E32+E33 -> 262144.26 | F55: =F32+F33 -> 284282 | G55: =G32+G33 -> 287893 | H55: =H32+H33 -> 290611 | I55: =I32+I33 -> 312699 | J55: =J32+J33 -> 289301 | K55: =K32+K33 -> 288963 | L55: Imobilizado + intangível: os bens que a empresa usa para produzir.
B56: Depreciação / ativo fixo do ano anterior | D56: =D21/C55 -> 0.067561055 | E56: =E21/D55 -> 0.075134944 | F56: =F21/E55 -> 0.062480864 | G56: =G21/F55 -> 0.057639949 | H56: =H21/G55 -> 0.053144745 | I56: =I21/H55 -> 0.056862954 | J56: =J21/I55 -> 0.055343957 | K56: =K21/J55 -> 0.061607115 | L56: Depreciação do ano dividida pelo ativo fixo do ano anterior: a velocidade do desgaste.
B57: Alíquota efetiva de imposto | C57: =-C17/C16 -> -0.038457335 | D57: =-D17/D16 -> 0.22391509 | E57: =-E17/E16 -> 0.10830552 | F57: =-F17/F16 -> 0.15909819 | G57: =-G17/G16 -> 0.14930583 | H57: =-H17/H16 -> 0.27000756 | I57: =-I17/I16 -> 0.11082866 | J57: =-J17/J16 -> 0.55752444 | K57: =-K17/K16 -> 0.64397198 | L57: Imposto de renda dividido pelo lucro antes do imposto: o que a empresa pagou de fato.
B58: Prazo médio de recebimento (dias) | C58: =C28/C6*365 -> 31.673417 | D58: =D28/D6*365 -> 28.198323 | E58: =E28/E6*365 -> 47.669051 | F58: =F28/F6*365 -> 27.158256 | G58: =G28/G6*365 -> 36.31662 | H58: =H28/H6*365 -> 35.641119 | I58: =I28/I6*365 -> 25.868304 | J58: =J28/J6*365 -> 21.598048 | K58: =K28/K6*365 -> 22.652968 | L58: Contas a receber ÷ receita × 365: quantos dias o cliente demora para pagar.
B59: Prazo médio de estoque (dias) | C59: =C29/-C45*365 -> 91.120088 | D59: =D29/-D45*365 -> 91.023981 | E59: =E29/-E45*365 -> 94.061208 | F59: =F29/-F45*365 -> 88.381026 | G59: =G29/-G45*365 -> 79.176043 | H59: =H29/-H45*365 -> 79.050336 | I59: =I29/-I45*365 -> 90.660972 | J59: =J29/-J45*365 -> 98.06705 | K59: =K29/-K45*365 -> 95.373928 | L59: Estoques ÷ custo caixa × 365: quantos dias o produto fica parado.
B60: Prazo médio de pagamento (dias) | C60: =C35/-C45*365 -> 72.033128 | D60: =D35/-D45*365 -> 87.469923 | E60: =E35/-E45*365 -> 77.98461 | F60: =F35/-F45*365 -> 70.161417 | G60: =G35/-G45*365 -> 78.810396 | H60: =H35/-H45*365 -> 88.963434 | I60: =I35/-I45*365 -> 83.360527 | J60: =J35/-J45*365 -> 91.927727 | K60: =K35/-K45*365 -> 94.459134 | L60: Fornecedores ÷ custo caixa × 365: quantos dias a empresa demora para pagar.
B61: Ciclo de caixa (dias) | C61: =C58+C59-C60 -> 50.760377 | D61: =D58+D59-D60 -> 31.752381 | E61: =E58+E59-E60 -> 63.745649 | F61: =F58+F59-F60 -> 45.377866 | G61: =G58+G59-G60 -> 36.682267 | H61: =H58+H59-H60 -> 25.72802 | I61: =I58+I59-I60 -> 33.168749 | J61: =J58+J59-J60 -> 27.73737 | K61: =K58+K59-K60 -> 23.567762 | L61: Prazo de recebimento + prazo de estoque − prazo de pagamento: dias que a empresa financia do próprio bolso.
B62: Capital de giro (receber + estoques - fornecedores) | C62: =C28+C29-C35 -> 15276.204 | D62: =D28+D29-D35 -> 12155.967 | E62: =E28+E29-E35 -> 30840.693 | F62: =F28+F29-F35 -> 26876 | G62: =G28+G29-G35 -> 22645 | H62: =H28+H29-H35 -> 17473 | I62: =I28+I29-I35 -> 16896 | J62: =J28+J29-J35 -> 14684 | K62: =K28+K29-K35 -> 13845 | L62: Contas a receber + estoques − fornecedores: dinheiro preso no dia a dia da operação.
B63: Caixa e aplicações | C63: =C26+C27 -> 22412.547 | D63: =D26+D27 -> 29627.092 | E63: =E26+E27 -> 70085.566 | F63: =F26+F27 -> 66437 | G63: =G26+G27 -> 25031 | H63: =H26+H27 -> 17724 | I63: =I26+I27 -> 31002 | J63: =J26+J27 -> 41629 | K63: =K26+K27 -> 29842 | L63: Caixa + aplicações financeiras.
B64: Dívida bruta | C64: =C36+C38 -> 59927.954 | D64: =D36+D38 -> 59842.73 | E64: =E36+E38 -> 78089.095 | F64: =F36+F38 -> 76909 | G64: =G36+G38 -> 66330 | H64: =H36+H38 -> 67404 | I64: =I36+I38 -> 96012 | J64: =J36+J38 -> 103457 | K64: =K36+K38 -> 98034 | L64: Empréstimos de curto prazo + empréstimos de longo prazo.
B65: Dívida líquida | C65: =C64-C63 -> 37515.407 | D65: =D64-D63 -> 30215.638 | E65: =E64-E63 -> 8003.529 | F65: =F64-F63 -> 10472 | G65: =G64-G63 -> 41299 | H65: =H64-H63 -> 49680 | I65: =I64-I63 -> 65010 | J65: =J64-J63 -> 61828 | K65: =K64-K63 -> 68192 | L65: Dívida bruta − caixa: o que a empresa deve depois de usar todo o dinheiro que tem.
B66: Dívida líquida / EBITDA | C66: =C65/C43 -> 0.67699403 | D66: =D65/D43 -> 1.7783834 | E66: =E65/E43 -> 0.11642033 | F66: =F65/F43 -> 0.066398671 | G66: =G65/G43 -> 0.38701364 | H66: =H65/H43 -> 0.61659137 | I66: =I65/I43 -> 0.90311736 | J66: =J65/J43 -> 1.2547539 | K66: =K65/K43 -> 1.3130765 | L66: Dívida líquida ÷ EBITDA: quantos anos de geração de caixa pagam a dívida. Acima de 3x é alto.
B67: Liquidez corrente | C67: =C30/C37 -> 1.6684033 | D67: =D30/D37 -> 1.2310143 | E67: =E30/E37 -> 1.6720639 | F67: =F30/F37 -> 1.4714552 | G67: =G30/G37 -> 1.1177047 | H67: =H30/H37 -> 1.2759909 | I67: =I30/I37 -> 1.0298686 | J67: =J30/J37 -> 1.1525996 | K67: =K30/K37 -> 1.1917526 | L67: Ativo circulante ÷ passivo circulante: acima de 1, o curto prazo está coberto.
B68: ROE (lucro dos controladores / patrimônio dos controladores) | C68: =C19/(C39-C40) -> 0.15056415 | D68: =D19/(D39-D40) -> -0.041314297 | E68: =E19/(E39-E40) -> 0.14378295 | F68: =F19/(F39-F40) -> 0.63007334 | G68: =G19/(G39-G40) -> 0.51265552 | H68: =H19/(H39-H40) -> 0.20914827 | I68: =I19/(I39-I40) -> 0.15278664 | J68: =J19/(J39-J40) -> 0.074954286 | K68: =K19/(K39-K40) -> 0.05273222 | L68: Lucro dos controladores ÷ patrimônio dos controladores: o retorno do dinheiro do sócio.
B69: ROIC (NOPAT / capital de giro + ativo fixo) | C69: =C47/(C62+C55) -> 0.1239413 | D69: =D47/(D62+D55) -> 0.013878632 | E69: =E47/(E62+E55) -> 0.12953683 | F69: =F47/(F62+F55) -> 0.31452227 | G69: =G47/(G62+G55) -> 0.18853924 | H69: =H47/(H62+H55) -> 0.15147155 | I69: =I47/(I62+I55) -> 0.11419815 | J69: =J47/(J62+J55) -> 0.071950063 | K69: =K47/(K62+K55) -> 0.075333479 | L69: NOPAT ÷ (capital de giro + ativo fixo): o retorno de todo o capital posto na operação.
B70: Caixa operacional menos capex | C70: =C22-C23 -> 33952.238 | D70: =D22-D23 -> 32509.785 | E70: =E22-E23 -> 52482.237 | F70: =F22-F23 -> 109465 | G70: =G22-G23 -> 30017 | H70: =H22-H23 -> 36459 | I70: =I22-I23 -> 15101 | J70: =J22-J23 -> 15375 | K70: =K22-K23 -> 18751 | L70: Caixa das operações − capex: o que sobra depois de investir.

Sheet Projeção
B1: ="Projeção - "&Painel!$D$5 -> Projeção - Vale (VALE3)
B2: DRE, investimento, capital de giro e balanço, ligados entre si. Custos e despesas em valor positivo. 2025 é o realizado; os outros anos são fórmulas.
B4: R$ milhões | C4: 2025 | D4: 2026E | E4: 2027E | F4: 2028E | G4: 2029E | H4: 2030E | I4: Como se calcula
B5: Do cenário para cada ano (vem do Painel)
B6: Crescimento da receita | D6: =Premissas!$C$7 -> 0.0209 | E6: =Painel!$C$10 -> 0.0378 | F6: =Painel!$C$10 -> 0.0378 | G6: =Painel!$C$10 -> 0.0378 | H6: =Painel!$C$10 -> 0.0378 | I6: 2026 repete os últimos doze meses. De 2027 em diante vale o crescimento escolhido no Painel.
B7: Margem EBITDA | D7: =Premissas!$C$8+(Painel!$C$11-Premissas!$C$8)*0/4 -> 0.3459 | E7: =Premissas!$C$8+(Painel!$C$11-Premissas!$C$8)*1/4 -> 0.357825 | F7: =Premissas!$C$8+(Painel!$C$11-Premissas!$C$8)*2/4 -> 0.36975 | G7: =Premissas!$C$8+(Painel!$C$11-Premissas!$C$8)*3/4 -> 0.381675 | H7: =Premissas!$C$8+(Painel!$C$11-Premissas!$C$8)*4/4 -> 0.3936 | I7: Sai da margem dos últimos doze meses em 2026 e chega, em linha reta, à margem escolhida no Painel em 2030.
B9: Demonstração do resultado
B10: Receita líquida | C10: =Demonstrativos!J6 -> 213595 | D10: =C10*(1+D6) -> 218059.14 | E10: =D10*(1+E6) -> 226301.77 | F10: =E10*(1+F6) -> 234855.98 | G10: =F10*(1+G6) -> 243733.53 | H10: =G10*(1+H6) -> 252946.66 | I10: Receita do ano anterior × (1 + crescimento).
B11: (-) Custo dos produtos (sem depreciação) | C11: =-Demonstrativos!J45 -> 121581 | D11: =D10-D12+D13-D14 -> 122963.57 | E11: =E10-E12+E13-E14 -> 125311.75 | F11: =F10-F12+F13-F14 -> 127659.5 | G11: =G10-G12+G13-G14 -> 130003.45 | H11: =H10-H12+H13-H14 -> 132339.96 | I11: O que sobra para a margem fechar: receita − despesas + equivalência − EBITDA.
B12: (-) Despesas operacionais (vendas, administrativas e outras) | C12: =-(Demonstrativos!J9+Demonstrativos!J10+Demonstrativos!J46) -> 41569 | D12: =D10*Premissas!$D$12 -> 18098.908 | E12: =E10*Premissas!$E$12 -> 18443.594 | F12: =F10*Premissas!$F$12 -> 18788.478 | G12: =G10*Premissas!$G$12 -> 19133.082 | H12: =H10*Premissas!$H$12 -> 19476.893 | I12: Receita × percentual de despesas operacionais (aba Premissas).
B13: (+/-) Equivalência patrimonial | C13: =Demonstrativos!J13 -> -1170 | D13: =Premissas!$D$13 -> -1570 | E13: =Premissas!$E$13 -> -1570 | F13: =Premissas!$F$13 -> -1570 | G13: =Premissas!$G$13 -> -1570 | H13: =Premissas!$H$13 -> -1570 | I13: Valor fixo da aba Premissas.
B14: EBITDA | C14: =C10-C11-C12+C13 -> 49275 | D14: =D10*D7 -> 75426.655 | E14: =E10*E7 -> 80976.431 | F14: =F10*F7 -> 86837.998 | G14: =G10*G7 -> 93026.996 | H14: =H10*H7 -> 99559.806 | I14: Receita × margem EBITDA do cenário.
B15: (-) Depreciação e amortização | C15: =Demonstrativos!J21 -> 17306 | D15: =C26*Premissas!$D$15 -> 16461.227 | E15: =D26*Premissas!$E$15 -> 17336.088 | F15: =E26*Premissas!$F$15 -> 18215.479 | G15: =F26*Premissas!$G$15 -> 19100.662 | H15: =G26*Premissas!$H$15 -> 19992.86 | I15: Ativo fixo do início do ano × taxa de depreciação (aba Premissas).
B16: EBIT | C16: =C14-C15 -> 31969 | D16: =D14-D15 -> 58965.428 | E16: =E14-E15 -> 63640.344 | F16: =F14-F15 -> 68622.519 | G16: =G14-G15 -> 73926.335 | H16: =H14-H15 -> 79566.946 | I16: EBITDA − depreciação.
B17: (+) Rendimento do caixa | D17: =C38*Premissas!$D$25 -> 3896.4744 | E17: =D38*Premissas!$D$25 -> 3693.0219 | F17: =E38*Premissas!$D$25 -> 3548.3343 | G17: =F38*Premissas!$D$25 -> 3488.3238 | H17: =G38*Premissas!$D$25 -> 3518.9725 | I17: Caixa do início do ano × rendimento do caixa.
B18: (-) Juros da dívida | D18: =C42*Premissas!$D$23 -> 5793.592 | E18: =D42*Premissas!$D$23 -> 5793.592 | F18: =E42*Premissas!$D$23 -> 5793.592 | G18: =F42*Premissas!$D$23 -> 5793.592 | H18: =G42*Premissas!$D$23 -> 5793.592 | I18: Dívida do início do ano × juros pagos sobre a dívida (aba Premissas).
B19: (+/-) Resultado financeiro | C19: =Demonstrativos!J15 -> -5276 | D19: =D17-D18 -> -1897.1176 | E19: =E17-E18 -> -2100.5701 | F19: =F17-F18 -> -2245.2577 | G19: =G17-G18 -> -2305.2682 | H19: =H17-H18 -> -2274.6195 | I19: Rendimento do caixa − juros da dívida.
B20: Lucro antes dos tributos | C20: =C16+C19 -> 26693 | D20: =D16+D19 -> 57068.31 | E20: =E16+E19 -> 61539.773 | F20: =F16+F19 -> 66377.261 | G20: =G16+G19 -> 71621.067 | H20: =H16+H19 -> 77292.326 | I20: EBIT + resultado financeiro.
B21: (-) Imposto de renda e CSLL | C21: =-Demonstrativos!J17 -> 14882 | D21: =MAX(0,D20-D13)*Premissas!$D$22 -> 19937.026 | E21: =MAX(0,E20-E13)*Premissas!$D$22 -> 21457.323 | F21: =MAX(0,F20-F13)*Premissas!$D$22 -> 23102.069 | G21: =MAX(0,G20-G13)*Premissas!$D$22 -> 24884.963 | H21: =MAX(0,H20-H13)*Premissas!$D$22 -> 26813.191 | I21: (Lucro antes do imposto − equivalência) × alíquota. Sem lucro, não há imposto.
B22: Lucro líquido | C22: =C20-C21 -> 11811 | D22: =D20-D21 -> 37131.285 | E22: =E20-E21 -> 40082.45 | F22: =F20-F21 -> 43275.192 | G22: =G20-G21 -> 46736.104 | H22: =H20-H21 -> 50479.135 | I22: Lucro antes do imposto − imposto.
B24: Investimento, depreciação e capital de giro
B25: Capex | C25: =Demonstrativos!J23 -> 33390 | D25: =D10*Premissas!$D$14 -> 31836.634 | E25: =E10*Premissas!$E$14 -> 32791.127 | F25: =F10*Premissas!$F$14 -> 33772.29 | G25: =G10*Premissas!$G$14 -> 34780.775 | H25: =H10*Premissas!$H$14 -> 35791.953 | I25: Receita × percentual de capex (aba Premissas).
B26: Ativo fixo (imobilizado + intangível) | C26: =Demonstrativos!J55 -> 289301 | D26: =C26+D25-D15 -> 304676.41 | E26: =D26+E25-E15 -> 320131.45 | F26: =E26+F25-F15 -> 335688.26 | G26: =F26+G25-G15 -> 351368.37 | H26: =G26+H25-H15 -> 367167.46 | I26: Ativo fixo anterior + capex − depreciação.
B27: Contas a receber | C27: =Demonstrativos!J28 -> 12639 | D27: =D10*Premissas!$D$16/365 -> 12903.127 | E27: =E10*Premissas!$E$16/365 -> 13390.865 | F27: =F10*Premissas!$F$16/365 -> 13897.039 | G27: =G10*Premissas!$G$16/365 -> 14422.348 | H27: =H10*Premissas!$H$16/365 -> 14967.512 | I27: Receita × prazo de recebimento ÷ 365.
B28: Estoques | C28: =Demonstrativos!J29 -> 32666 | D28: =D11*Premissas!$D$17/365 -> 33037.448 | E28: =E11*Premissas!$E$17/365 -> 33668.348 | F28: =F11*Premissas!$F$17/365 -> 34299.135 | G28: =G11*Premissas!$G$17/365 -> 34928.901 | H28: =H11*Premissas!$H$17/365 -> 35556.666 | I28: Custo dos produtos × prazo de estoque ÷ 365.
B29: Fornecedores | C29: =Demonstrativos!J35 -> 30621 | D29: =D11*Premissas!$D$18/365 -> 30969.201 | E29: =E11*Premissas!$E$18/365 -> 31560.604 | F29: =F11*Premissas!$F$18/365 -> 32151.902 | G29: =G11*Premissas!$G$18/365 -> 32742.243 | H29: =H11*Premissas!$H$18/365 -> 33330.708 | I29: Custo dos produtos × prazo de pagamento ÷ 365.
B30: Capital de giro | C30: =C27+C28-C29 -> 14684 | D30: =D27+D28-D29 -> 14971.374 | E30: =E27+E28-E29 -> 15498.608 | F30: =F27+F28-F29 -> 16044.272 | G30: =G27+G28-G29 -> 16609.006 | H30: =H27+H28-H29 -> 17193.47 | I30: Contas a receber + estoques − fornecedores.
B31: Variação do capital de giro (investimento em giro) | D31: =D30-C30 -> 287.37388 | E31: =E30-D30 -> 527.23446 | F31: =F30-E30 -> 545.66395 | G31: =G30-F30 -> 564.73338 | H31: =H30-G30 -> 584.4648 | I31: Capital de giro do ano − o do ano anterior. Positivo consome caixa.
B33: Do lucro ao caixa
B34: (-) Dividendos | D34: =MAX(0,D22)*Premissas!$D$26 -> 25212.142 | E34: =MAX(0,E22)*Premissas!$D$26 -> 27215.984 | F34: =MAX(0,F22)*Premissas!$D$26 -> 29383.855 | G34: =MAX(0,G22)*Premissas!$D$26 -> 31733.815 | H34: =MAX(0,H22)*Premissas!$D$26 -> 34275.333 | I34: Lucro líquido × percentual distribuído (aba Premissas). Sem lucro, não há dividendo.
B35: Variação do caixa (FCFE da aba FCFF menos dividendos) | D35: =FCFF!D22-D34 -> -2173.6383 | E35: =FCFF!E22-E34 -> -1545.8069 | F35: =FCFF!F22-F34 -> -641.1376 | G35: =FCFF!G22-G34 -> 327.4425 | H35: =FCFF!H22-H34 -> 1390.2453 | I35: FCFE − dividendos: o que entra ou sai do caixa no ano.
B37: Balanço patrimonial resumido
B38: Caixa e aplicações | C38: =Demonstrativos!J63 -> 41629 | D38: =C38+D35 -> 39455.362 | E38: =D38+E35 -> 37909.555 | F38: =E38+F35 -> 37268.417 | G38: =F38+G35 -> 37595.86 | H38: =G38+H35 -> 38986.105 | I38: Caixa anterior + variação do caixa. É a conta que fecha o balanço.
B39: Investimentos em coligadas | C39: =Demonstrativos!J31 -> 27674 | D39: =C39+D13 -> 26104 | E39: =D39+E13 -> 24534 | F39: =E39+F13 -> 22964 | G39: =F39+G13 -> 21394 | H39: =G39+H13 -> 19824 | I39: Saldo anterior + equivalência do ano.
B40: Outros ativos (mantidos) | C40: =Demonstrativos!J34-C38-C27-C28-C26-C39 -> 72185 | D40: =C40 -> 72185 | E40: =D40 -> 72185 | F40: =E40 -> 72185 | G40: =F40 -> 72185 | H40: =G40 -> 72185 | I40: Tudo o que o modelo não projeta linha a linha; fica constante.
B41: Ativo total | C41: =C38+C27+C28+C26+C39+C40 -> 476094 | D41: =D38+D27+D28+D26+D39+D40 -> 488361.34 | E41: =E38+E27+E28+E26+E39+E40 -> 501819.21 | F41: =F38+F27+F28+F26+F39+F40 -> 516301.85 | G41: =G38+G27+G28+G26+G39+G40 -> 531894.48 | H41: =H38+H27+H28+H26+H39+H40 -> 548686.75 | I41: Soma de todas as linhas do ativo.
B42: Dívida bruta | C42: =Demonstrativos!J64 -> 103457 | D42: =C42+Premissas!$D$19 -> 103457 | E42: =D42+Premissas!$E$19 -> 103457 | F42: =E42+Premissas!$F$19 -> 103457 | G42: =F42+Premissas!$G$19 -> 103457 | H42: =G42+Premissas!$H$19 -> 103457 | I42: Dívida anterior + captação líquida (aba Premissas).
B43: Outros passivos (mantidos) | C43: =Demonstrativos!J34-C29-C42-C44 -> 153090 | D43: =C43 -> 153090 | E43: =D43 -> 153090 | F43: =E43 -> 153090 | G43: =F43 -> 153090 | H43: =G43 -> 153090 | I43: Tudo o que o modelo não projeta linha a linha; fica constante.
B44: Patrimônio líquido | C44: =Demonstrativos!J39 -> 188926 | D44: =C44+D22-D34 -> 200845.14 | E44: =D44+E22-E34 -> 213711.61 | F44: =E44+F22-F34 -> 227602.95 | G44: =F44+G22-G34 -> 242605.24 | H44: =G44+H22-H34 -> 258809.04 | I44: Patrimônio anterior + lucro líquido − dividendos.
B45: Passivo + patrimônio líquido | C45: =C29+C42+C43+C44 -> 476094 | D45: =D29+D42+D43+D44 -> 488361.34 | E45: =E29+E42+E43+E44 -> 501819.21 | F45: =F29+F42+F43+F44 -> 516301.85 | G45: =G29+G42+G43+G44 -> 531894.48 | H45: =H29+H42+H43+H44 -> 548686.75 | I45: Fornecedores + dívida + outros passivos + patrimônio líquido.
B46: Checagem: ativo - passivo (tem de ser zero) | C46: =ROUND(C41-C45,3) -> 0 | D46: =ROUND(D41-D45,3) -> 0 | E46: =ROUND(E41-E45,3) -> 0 | F46: =ROUND(F41-F45,3) -> 0 | G46: =ROUND(G41-G45,3) -> 0 | H46: =ROUND(H41-H45,3) -> 0 | I46: Ativo − (passivo + patrimônio). Se não der zero, há erro no modelo.
B48: Indicadores
B49: Margem EBIT | C49: =C16/C10 -> 0.14967111 | D49: =D16/D10 -> 0.27041026 | E49: =E16/E10 -> 0.28121894 | F49: =F16/F10 -> 0.29218979 | G49: =G16/G10 -> 0.30330802 | H49: =H16/H10 -> 0.31456017 | I49: EBIT ÷ receita.
B50: Dívida líquida | C50: =C42-C38 -> 61828 | D50: =D42-D38 -> 64001.638 | E50: =E42-E38 -> 65547.445 | F50: =F42-F38 -> 66188.583 | G50: =G42-G38 -> 65861.14 | H50: =H42-H38 -> 64470.895 | I50: Dívida bruta − caixa.
B51: Dívida líquida / EBITDA | C51: =C50/C14 -> 1.2547539 | D51: =D50/D14 -> 0.84852813 | E51: =E50/E14 -> 0.80946325 | F51: =F50/F14 -> 0.76220761 | G51: =G50/G14 -> 0.70797879 | H51: =H50/H14 -> 0.64755947 | I51: Dívida líquida ÷ EBITDA.
B52: ROIC (NOPAT / capital investido inicial) | D52: =FCFF!D9/(C30+C26) -> 0.13143209 | E52: =FCFF!E9/(D30+D26) -> 0.13464453 | F52: =FCFF!F9/(E30+E26) -> 0.13803014 | G52: =FCFF!G9/(F30+F26) -> 0.14166327 | H52: =FCFF!H9/(G30+G26) -> 0.1455263 | I52: NOPAT ÷ (capital de giro + ativo fixo do início do ano).

Sheet FCFF
B1: ="FCFF e FCFE - "&Painel!$D$5 -> FCFF e FCFE - Vale (VALE3)
B2: O caixa livre de cada ano, que é o ponto de partida do valuation. FCFF é o caixa da empresa inteira; FCFE é a parte do acionista.
B4: R$ milhões | D4: 2026E | E4: 2027E | F4: 2028E | G4: 2029E | H4: 2030E | I4: O que é e como se calcula
B5: FCFF: o caixa livre da empresa, para credores e acionistas
B6: EBIT | D6: =Projeção!D16 -> 58965.428 | E6: =Projeção!E16 -> 63640.344 | F6: =Projeção!F16 -> 68622.519 | G6: =Projeção!G16 -> 73926.335 | H6: =Projeção!H16 -> 79566.946 | I6: Lucro da operação antes de juros e impostos (aba Projeção).
B7: (-) Equivalência patrimonial | D7: =Projeção!D13 -> -1570 | E7: =Projeção!E13 -> -1570 | F7: =Projeção!F13 -> -1570 | G7: =Projeção!G13 -> -1570 | H7: =Projeção!H13 -> -1570 | I7: Sai da conta: é lucro de outras empresas, não entra no caixa desta.
B8: (-) Imposto sobre o lucro da operação | D8: =(D6-D7)*Premissas!$D$22 -> 20582.046 | E8: =(E6-E7)*Premissas!$D$22 -> 22171.517 | F8: =(F6-F7)*Premissas!$D$22 -> 23865.456 | G8: =(G6-G7)*Premissas!$D$22 -> 25668.754 | H8: =(H6-H7)*Premissas!$D$22 -> 27586.562 | I8: (EBIT − equivalência) × alíquota: o imposto que a operação pagaria sem dívida.
B9: (=) NOPAT | D9: =D6-D7-D8 -> 39953.383 | E9: =E6-E7-E8 -> 43038.827 | F9: =F6-F7-F8 -> 46327.062 | G9: =G6-G7-G8 -> 49827.581 | H9: =H6-H7-H8 -> 53550.384 | I9: EBIT − equivalência − imposto: o lucro da operação depois do imposto.
B10: (+) Depreciação e amortização | D10: =Projeção!D15 -> 16461.227 | E10: =Projeção!E15 -> 17336.088 | F10: =Projeção!F15 -> 18215.479 | G10: =Projeção!G15 -> 19100.662 | H10: =Projeção!H15 -> 19992.86 | I10: Volta para a conta: foi descontada no EBIT, mas não saiu do caixa.
B11: (-) Capex | D11: =Projeção!D25 -> 31836.634 | E11: =Projeção!E25 -> 32791.127 | F11: =Projeção!F25 -> 33772.29 | G11: =Projeção!G25 -> 34780.775 | H11: =Projeção!H25 -> 35791.953 | I11: Sai da conta: dinheiro investido em ativos.
B12: (-) Variação do capital de giro | D12: =Projeção!D31 -> 287.37388 | E12: =Projeção!E31 -> 527.23446 | F12: =Projeção!F31 -> 545.66395 | G12: =Projeção!G31 -> 564.73338 | H12: =Projeção!H31 -> 584.4648 | I12: Sai da conta: dinheiro a mais preso em clientes e estoques.
B13: (=) FCFF | D13: =D9+D10-D11-D12 -> 24290.602 | E13: =E9+E10-E11-E12 -> 27056.553 | F13: =F9+F10-F11-F12 -> 30224.588 | G13: =G9+G10-G11-G12 -> 33582.734 | H13: =H9+H10-H11-H12 -> 37166.827 | I13: NOPAT + depreciação − capex − variação do giro. É o caixa livre para credores e acionistas.
B15: FCFE: o caixa livre só do acionista
B16: Lucro líquido | D16: =Projeção!D22 -> 37131.285 | E16: =Projeção!E22 -> 40082.45 | F16: =Projeção!F22 -> 43275.192 | G16: =Projeção!G22 -> 46736.104 | H16: =Projeção!H22 -> 50479.135 | I16: Lucro depois de juros e impostos (aba Projeção).
B17: (-) Equivalência patrimonial | D17: =Projeção!D13 -> -1570 | E17: =Projeção!E13 -> -1570 | F17: =Projeção!F13 -> -1570 | G17: =Projeção!G13 -> -1570 | H17: =Projeção!H13 -> -1570 | I17: Sai da conta: é lucro de outras empresas, não entra no caixa desta.
B18: (+) Depreciação e amortização | D18: =Projeção!D15 -> 16461.227 | E18: =Projeção!E15 -> 17336.088 | F18: =Projeção!F15 -> 18215.479 | G18: =Projeção!G15 -> 19100.662 | H18: =Projeção!H15 -> 19992.86 | I18: Volta para a conta: foi descontada no EBIT, mas não saiu do caixa.
B19: (-) Capex | D19: =Projeção!D25 -> 31836.634 | E19: =Projeção!E25 -> 32791.127 | F19: =Projeção!F25 -> 33772.29 | G19: =Projeção!G25 -> 34780.775 | H19: =Projeção!H25 -> 35791.953 | I19: Sai da conta: dinheiro investido em ativos.
B20: (-) Variação do capital de giro | D20: =Projeção!D31 -> 287.37388 | E20: =Projeção!E31 -> 527.23446 | F20: =Projeção!F31 -> 545.66395 | G20: =Projeção!G31 -> 564.73338 | H20: =Projeção!H31 -> 584.4648 | I20: Sai da conta: dinheiro a mais preso em clientes e estoques.
B21: (+) Captação líquida de dívida | D21: =Premissas!$D$19 -> 0 | E21: =Premissas!$E$19 -> 0 | F21: =Premissas!$F$19 -> 0 | G21: =Premissas!$G$19 -> 0 | H21: =Premissas!$H$19 -> 0 | I21: Dívida nova menos dívida paga no ano.
B22: (=) FCFE | D22: =D16-D17+D18-D19-D20+D21 -> 23038.504 | E22: =E16-E17+E18-E19-E20+E21 -> 25670.177 | F22: =F16-F17+F18-F19-F20+F21 -> 28742.718 | G22: =G16-G17+G18-G19-G20+G21 -> 32061.257 | H22: =H16-H17+H18-H19-H20+H21 -> 35665.578 | I22: Lucro líquido − equivalência + depreciação − capex − variação do giro + captação. É o caixa livre só do acionista.
B24: Fluxo de 2030 ajustado para a perpetuidade
B25: Capex de reposição | D25: =Premissas!$D$33*H10 -> 19992.86 | I25: Depois de 2030 a empresa só repõe o que desgasta: depreciação × múltiplo da aba Premissas.
B26: FCFF normalizado de 2030 | D26: =H9+H10-D25-H12 -> 52965.919 | I26: FCFF de 2030 com o capex de reposição no lugar do capex do ano.
B27: FCFE normalizado de 2030 | D27: =H16-H17+H18-D25-H20+H21 -> 51464.67 | I27: FCFE de 2030 com o capex de reposição no lugar do capex do ano.

Sheet WACC
B1: ="Custo de capital - "&Painel!$D$5 -> Custo de capital - Vale (VALE3)
B2: CAPM para o capital próprio; WACC é a média com o custo da dívida depois do imposto.
B4: Capital próprio (CAPM) | D4: Valor | E4: O que é e como se calcula
B5: Juro sem risco (Rf) | D5: =Premissas!$D$27 -> 0.1291 | E5: O juro de um investimento sem risco de calote: o título do Tesouro prefixado de dez anos.
B6: Beta | D6: =Premissas!$D$28 -> 0.7558 | E6: Quanto a ação costuma andar quando a bolsa anda 1%. Acima de 1, oscila mais que o mercado.
B7: Prêmio de risco de mercado | D7: =Premissas!$D$29 -> 0.0423 | E7: O retorno a mais que o investidor exige para estar em ações em vez de títulos do governo.
B8: Prêmio adicional | D8: =Premissas!$D$30 -> 0 | E8: Prêmio extra por risco próprio da empresa. Zero nesta versão.
B9: Custo do capital próprio (Ke) | D9: =D5+D6*D7+D8 -> 0.16107034 | E9: Ke = juro sem risco + beta × prêmio de mercado + prêmio adicional. É o retorno que o acionista exige.
B11: Dívida | D11: Valor | E11: O que é e como se calcula
B12: Custo da dívida antes do imposto (Kd) | D12: =Premissas!$D$24 -> 0.0715 | E12: O que a dívida custa à empresa, em reais. Vem do custo que ela divulga (aba Premissas).
B13: Alíquota de IR e CSLL | D13: =Premissas!$D$22 -> 0.34 | E13: Alíquota de imposto sobre o lucro.
B14: Custo da dívida após o imposto | D14: =D12*(1-D13) -> 0.04719 | E14: Kd × (1 − alíquota). O juro reduz o imposto a pagar, então a dívida custa menos.
B16: Média ponderada | D16: Valor | E16: O que é e como se calcula
B17: Peso da dívida | D17: =Premissas!$D$31 -> 0.2625 | E17: Quanto do capital da empresa vem de dívida.
B18: Peso do capital próprio | D18: =1-D17 -> 0.7375 | E18: 1 − peso da dívida: quanto do capital vem dos sócios.
B19: WACC pelo CAPM | D19: =D9*D18+D14*D17 -> 0.13117675 | E19: Ke × peso dos sócios + Kd após imposto × peso da dívida. É o custo médio do capital.
B21: Cenário (vem do Painel) | D21: Valor | E21: O que é e como se calcula
B22: WACC em uso | D22: =Painel!$C$12 -> 0.13117675 | E22: A taxa escolhida no Painel. É ela que desconta o FCFF.
B23: Diferença para o CAPM | D23: =D22-D19 -> 0 | E23: WACC em uso − WACC do CAPM: quanto o cenário ou o ajuste manual deslocou a taxa.
B24: Ke em uso | D24: =D9+D23 -> 0.16107034 | E24: Ke + o mesmo ajuste. É a taxa que desconta o FCFE.
B26: Referência: estrutura a valor de mercado | D26: Valor | E26: O que é e como se calcula
B27: Valor de mercado (R$ milhões) | D27: =Premissas!$D$40 -> 275454.84 | E27: Preço da ação × número de ações.
B28: Dívida bruta na data-base (R$ milhões) | D28: =Demonstrativos!K64 -> 98034 | E28: Dívida bruta no último balanço.
B29: Peso da dívida a valor de mercado | D29: =D28/(D28+D27) -> 0.26248174 | E29: Dívida ÷ (dívida + valor de mercado): serve para conferir o peso usado.

Sheet Valor justo
B1: ="Valor justo - "&Painel!$D$5 -> Valor justo - Vale (VALE3)
B2: Os fluxos de caixa trazidos a valor de hoje, o valor da empresa, o valor do acionista e o preço por ação.
B4: R$ milhões | D4: 2026E | E4: 2027E | F4: 2028E | G4: 2029E | H4: 2030E | I4: O que é e como se calcula
B5: Fluxo da empresa (FCFF), descontado pelo WACC
B6: FCFF | D6: =FCFF!D13 -> 24290.602 | E6: =FCFF!E13 -> 27056.553 | F6: =FCFF!F13 -> 30224.588 | G6: =FCFF!G13 -> 33582.734 | H6: =FCFF!H13 -> 37166.827 | I6: O caixa livre de cada ano (aba FCFF).
B7: Parte do ano que entra no valor | D7: =(DATE(2026,12,31)-Premissas!$D$37)/365 -> 0.50410959 | E7: 1 | F7: 1 | G7: 1 | H7: 1 | I7: De 2026 só conta a parte do ano que vem depois do último balanço. Os outros anos contam inteiros.
B8: Fim do período (anos desde a data-base) | D8: =D7 -> 0.50410959 | E8: =D8+1 -> 1.5041096 | F8: =E8+1 -> 2.5041096 | G8: =F8+1 -> 3.5041096 | H8: =G8+1 -> 4.5041096 | I8: Quantos anos faltam, a partir do último balanço, até o fim de cada ano.
B9: Meio do período (quando o caixa entra, em média) | D9: =D8-D7/2 -> 0.25205479 | E9: =E8-E7/2 -> 1.0041096 | F9: =F8-F7/2 -> 2.0041096 | G9: =G8-G7/2 -> 3.0041096 | H9: =H8-H7/2 -> 4.0041096 | I9: O caixa entra ao longo do ano, não no último dia: usa-se o meio do período.
B10: Fator de desconto | D10: =1/(1+WACC!$D$22)^D9 -> 0.96940976 | E10: =1/(1+WACC!$D$22)^E9 -> 0.88358746 | F10: =1/(1+WACC!$D$22)^F9 -> 0.78112236 | G10: =1/(1+WACC!$D$22)^G9 -> 0.69053962 | H10: =1/(1+WACC!$D$22)^H9 -> 0.61046129 | I10: 1 ÷ (1 + WACC) elevado ao número de anos. Quanto vale hoje R$ 1 recebido naquela data.
B11: Valor presente do fluxo | D11: =D6*D7*D10 -> 11870.544 | E11: =E6*E7*E10 -> 23906.831 | F11: =F6*F7*F10 -> 23609.102 | G11: =G6*G7*G10 -> 23190.208 | H11: =H6*H7*H10 -> 22688.909 | I11: FCFF × parte do ano × fator de desconto.
B13: Perpetuidade (Gordon)
B14: WACC | D14: =WACC!$D$22 -> 0.13117675 | I14: A taxa de desconto em uso (aba WACC).
B15: Crescimento na perpetuidade (g) | D15: =Premissas!$D$32 -> 0.035 | I15: A taxa à qual o caixa cresce para sempre depois de 2030 (aba Premissas).
B16: FCFF normalizado de 2030 | D16: =FCFF!D26 -> 52965.919 | I16: O FCFF de 2030 ajustado para repetir para sempre (aba FCFF).
B17: Valor terminal no fim do último ano | D17: =D16*(1+D15)/(D14-D15) -> 569989.38 | I17: FCFF normalizado × (1 + g) ÷ (WACC − g). Resume em um número todos os anos depois de 2030.
B18: Valor presente do valor terminal | D18: =D17/(1+D14)^H8 -> 327159.59 | I18: Valor terminal ÷ (1 + WACC) elevado aos anos até o fim de 2030.
B20: Do valor da empresa ao preço por ação
B21: Valor presente dos fluxos projetados | D21: =SUM($D$11:$H$11) -> 105265.59 | I21: Soma dos valores presentes de 2026 a 2030.
B22: Valor da empresa (Enterprise Value) | D22: =D21+D18 -> 432425.19 | I22: Valor presente dos fluxos + valor presente do valor terminal. Quanto vale a operação inteira.
B23: (-) Dívida líquida na data-base | D23: =Demonstrativos!K65 -> 68192 | I23: Sai: é dos credores (dívida bruta − caixa, no último balanço).
B24: (-) Participação de não controladores | D24: =Demonstrativos!K40 -> 4832 | I24: Sai: é dos sócios das controladas.
B25: (+) Investimentos em coligadas (valor contábil) | D25: =Demonstrativos!K31 -> 27248 | I25: Entra: participações em outras empresas, que o FCFF não contou.
B26: (-) Outros passivos tratados como dívida | D26: =Premissas!$D$34 -> 0 | I26: Sai: outros passivos que funcionam como dívida (aba Premissas).
B27: Valor do acionista (Equity Value) | D27: =D22-D23-D24+D25-D26 -> 386649.19 | I27: EV − dívida líquida − minoritários + investimentos − outros. Quanto vale a parte dos acionistas.
B28: Ações em circulação (milhões) | D28: =Premissas!$D$38 -> 4072.366 | I28: Número de ações em circulação, sem as que estão na tesouraria.
B29: Preço justo por ação | D29: =D27/D28 -> 94.944606 | I29: Valor do acionista ÷ número de ações.
B30: Preço de mercado | D30: =Premissas!$D$39 -> 67.64 | I30: Último fechamento na B3.
B31: Diferença para o preço de mercado | D31: =D29/D30-1 -> 0.40367543 | I31: Preço justo ÷ preço de mercado − 1.
B32: Peso do valor terminal no valor da empresa | D32: =D18/D22 -> 0.75656923 | I32: Quanto do valor da empresa vem de depois de 2030. Quanto maior, mais o resultado depende do longo prazo.
B33: EV / EBITDA 2026E implícito | D33: =D22/Projeção!D14 -> 5.7330553 | I33: Valor da empresa ÷ EBITDA de 2026: o múltiplo que o DCF está pagando.
B35: Conferência pelo fluxo do acionista (FCFE), descontado pelo Ke
B36: FCFE | D36: =FCFF!D22 -> 23038.504 | E36: =FCFF!E22 -> 25670.177 | F36: =FCFF!F22 -> 28742.718 | G36: =FCFF!G22 -> 32061.257 | H36: =FCFF!H22 -> 35665.578 | I36: O caixa livre do acionista de cada ano (aba FCFF).
B37: Fator de desconto pelo Ke | D37: =1/(1+WACC!$D$24)^D9 -> 0.96305723 | E37: =1/(1+WACC!$D$24)^E9 -> 0.86074583 | F37: =1/(1+WACC!$D$24)^F9 -> 0.74133823 | G37: =1/(1+WACC!$D$24)^G9 -> 0.63849554 | H37: =1/(1+WACC!$D$24)^H9 -> 0.54991977 | I37: 1 ÷ (1 + Ke) elevado ao número de anos.
B38: Valor presente do FCFE | D38: =D36*D7*D37 -> 11184.88 | E38: =E36*E7*E37 -> 22095.498 | F38: =F36*F7*F37 -> 21308.076 | G38: =G36*G7*G37 -> 20470.97 | H38: =H36*H7*H37 -> 19613.207 | I38: FCFE × parte do ano × fator de desconto.
B39: Custo do capital próprio (Ke) em uso | D39: =WACC!$D$24 -> 0.16107034 | I39: A taxa que desconta o caixa do acionista (aba WACC).
B40: FCFE normalizado de 2030 | D40: =FCFF!D27 -> 51464.67 | I40: O FCFE de 2030 ajustado para repetir para sempre (aba FCFF).
B41: Valor presente do valor terminal do FCFE | D41: =D40*(1+D15)/(D39-D15)/(1+D39)^H8 -> 215628.76 | I41: Valor terminal do FCFE trazido a valor de hoje pelo Ke.
B42: Valor do acionista pelo FCFE | D42: =SUM($D$38:$H$38)+D41-D24+D25-D26 -> 332717.39 | I42: Soma dos FCFE descontados, menos minoritários, mais investimentos. Deve ficar perto do valor pelo FCFF.
B43: Preço por ação pelo FCFE | D43: =D42/D28 -> 81.70125 | I43: Valor do acionista pelo FCFE ÷ número de ações.
B45: Sensibilidade do preço justo: WACC (linhas) x crescimento perpétuo (colunas)
C46: WACC \ g | D46: =$D$15+-2*0.005 -> 0.025 | E46: =$D$15+-1*0.005 -> 0.03 | F46: =$D$15+0*0.005 -> 0.035 | G46: =$D$15+1*0.005 -> 0.04 | H46: =$D$15+2*0.005 -> 0.045 | I46: Cada célula refaz a conta inteira com o WACC da linha e o g da coluna. A do meio é o preço justo.
C47: =$D$14+-2*0.01 -> 0.11117675 | D47: =(SUMPRODUCT($D$6:$H$6*$D$7:$H$7/(1+$C47)^$D$9:$H$9)+$D$16*(1+D$46)/($C47-D$46)/(1+$C47)^$H$8-$D$23-$D$24+$D$25-$D$26)/$D$28 -> 111.88566 | E47: =(SUMPRODUCT($D$6:$H$6*$D$7:$H$7/(1+$C47)^$D$9:$H$9)+$D$16*(1+E$46)/($C47-E$46)/(1+$C47)^$H$8-$D$23-$D$24+$D$25-$D$26)/$D$28 -> 118.3106 | F47: =(SUMPRODUCT($D$6:$H$6*$D$7:$H$7/(1+$C47)^$D$9:$H$9)+$D$16*(1+F$46)/($C47-F$46)/(1+$C47)^$H$8-$D$23-$D$24+$D$25-$D$26)/$D$28 -> 125.57896 | G47: =(SUMPRODUCT($D$6:$H$6*$D$7:$H$7/(1+$C47)^$D$9:$H$9)+$D$16*(1+G$46)/($C47-G$46)/(1+$C47)^$H$8-$D$23-$D$24+$D$25-$D$26)/$D$28 -> 133.86849 | H47: =(SUMPRODUCT($D$6:$H$6*$D$7:$H$7/(1+$C47)^$D$9:$H$9)+$D$16*(1+H$46)/($C47-H$46)/(1+$C47)^$H$8-$D$23-$D$24+$D$25-$D$26)/$D$28 -> 143.41066
C48: =$D$14+-1*0.01 -> 0.12117675 | D48: =(SUMPRODUCT($D$6:$H$6*$D$7:$H$7/(1+$C48)^$D$9:$H$9)+$D$16*(1+D$46)/($C48-D$46)/(1+$C48)^$H$8-$D$23-$D$24+$D$25-$D$26)/$D$28 -> 97.933713 | E48: =(SUMPRODUCT($D$6:$H$6*$D$7:$H$7/(1+$C48)^$D$9:$H$9)+$D$16*(1+E$46)/($C48-E$46)/(1+$C48)^$H$8-$D$23-$D$24+$D$25-$D$26)/$D$28 -> 102.9008 | F48: =(SUMPRODUCT($D$6:$H$6*$D$7:$H$7/(1+$C48)^$D$9:$H$9)+$D$16*(1+F$46)/($C48-F$46)/(1+$C48)^$H$8-$D$23-$D$24+$D$25-$D$26)/$D$28 -> 108.44428 | G48: =(SUMPRODUCT($D$6:$H$6*$D$7:$H$7/(1+$C48)^$D$9:$H$9)+$D$16*(1+G$46)/($C48-G$46)/(1+$C48)^$H$8-$D$23-$D$24+$D$25-$D$26)/$D$28 -> 114.67064 | H48: =(SUMPRODUCT($D$6:$H$6*$D$7:$H$7/(1+$C48)^$D$9:$H$9)+$D$16*(1+H$46)/($C48-H$46)/(1+$C48)^$H$8-$D$23-$D$24+$D$25-$D$26)/$D$28 -> 121.71436
C49: =$D$14+0*0.01 -> 0.13117675 | D49: =(SUMPRODUCT($D$6:$H$6*$D$7:$H$7/(1+$C49)^$D$9:$H$9)+$D$16*(1+D$46)/($C49-D$46)/(1+$C49)^$H$8-$D$23-$D$24+$D$25-$D$26)/$D$28 -> 86.675215 | E49: =(SUMPRODUCT($D$6:$H$6*$D$7:$H$7/(1+$C49)^$D$9:$H$9)+$D$16*(1+E$46)/($C49-E$46)/(1+$C49)^$H$8-$D$23-$D$24+$D$25-$D$26)/$D$28 -> 90.60558 | F49: =(SUMPRODUCT($D$6:$H$6*$D$7:$H$7/(1+$C49)^$D$9:$H$9)+$D$16*(1+F$46)/($C49-F$46)/(1+$C49)^$H$8-$D$23-$D$24+$D$25-$D$26)/$D$28 -> 94.944606 | G49: =(SUMPRODUCT($D$6:$H$6*$D$7:$H$7/(1+$C49)^$D$9:$H$9)+$D$16*(1+G$46)/($C49-G$46)/(1+$C49)^$H$8-$D$23-$D$24+$D$25-$D$26)/$D$28 -> 99.759524 | H49: =(SUMPRODUCT($D$6:$H$6*$D$7:$H$7/(1+$C49)^$D$9:$H$9)+$D$16*(1+H$46)/($C49-H$46)/(1+$C49)^$H$8-$D$23-$D$24+$D$25-$D$26)/$D$28 -> 105.13317
C50: =$D$14+1*0.01 -> 0.14117675 | D50: =(SUMPRODUCT($D$6:$H$6*$D$7:$H$7/(1+$C50)^$D$9:$H$9)+$D$16*(1+D$46)/($C50-D$46)/(1+$C50)^$H$8-$D$23-$D$24+$D$25-$D$26)/$D$28 -> 77.411025 | E50: =(SUMPRODUCT($D$6:$H$6*$D$7:$H$7/(1+$C50)^$D$9:$H$9)+$D$16*(1+E$46)/($C50-E$46)/(1+$C50)^$H$8-$D$23-$D$24+$D$25-$D$26)/$D$28 -> 80.580706 | F50: =(SUMPRODUCT($D$6:$H$6*$D$7:$H$7/(1+$C50)^$D$9:$H$9)+$D$16*(1+F$46)/($C50-F$46)/(1+$C50)^$H$8-$D$23-$D$24+$D$25-$D$26)/$D$28 -> 84.048916 | G50: =(SUMPRODUCT($D$6:$H$6*$D$7:$H$7/(1+$C50)^$D$9:$H$9)+$D$16*(1+G$46)/($C50-G$46)/(1+$C50)^$H$8-$D$23-$D$24+$D$25-$D$26)/$D$28 -> 87.859914 | H50: =(SUMPRODUCT($D$6:$H$6*$D$7:$H$7/(1+$C50)^$D$9:$H$9)+$D$16*(1+H$46)/($C50-H$46)/(1+$C50)^$H$8-$D$23-$D$24+$D$25-$D$26)/$D$28 -> 92.067161
C51: =$D$14+2*0.01 -> 0.15117675 | D51: =(SUMPRODUCT($D$6:$H$6*$D$7:$H$7/(1+$C51)^$D$9:$H$9)+$D$16*(1+D$46)/($C51-D$46)/(1+$C51)^$H$8-$D$23-$D$24+$D$25-$D$26)/$D$28 -> 69.663866 | E51: =(SUMPRODUCT($D$6:$H$6*$D$7:$H$7/(1+$C51)^$D$9:$H$9)+$D$16*(1+E$46)/($C51-E$46)/(1+$C51)^$H$8-$D$23-$D$24+$D$25-$D$26)/$D$28 -> 72.260871 | F51: =(SUMPRODUCT($D$6:$H$6*$D$7:$H$7/(1+$C51)^$D$9:$H$9)+$D$16*(1+F$46)/($C51-F$46)/(1+$C51)^$H$8-$D$23-$D$24+$D$25-$D$26)/$D$28 -> 75.081415 | G51: =(SUMPRODUCT($D$6:$H$6*$D$7:$H$7/(1+$C51)^$D$9:$H$9)+$D$16*(1+G$46)/($C51-G$46)/(1+$C51)^$H$8-$D$23-$D$24+$D$25-$D$26)/$D$28 -> 78.155659 | H51: =(SUMPRODUCT($D$6:$H$6*$D$7:$H$7/(1+$C51)^$D$9:$H$9)+$D$16*(1+H$46)/($C51-H$46)/(1+$C51)^$H$8-$D$23-$D$24+$D$25-$D$26)/$D$28 -> 81.519442

Sheet Múltiplos
B1: Valuation por múltiplos
B2: Quanto o mercado paga pelas comparáveis, com os números dos últimos doze meses. A mediana das outras quatro, aplicada à empresa escolhida, dá um preço implícito.
B4: Empresa (R$ milhões) | C4: Setor | D4: Preço | E4: Ações (milhões) | F4: Valor de mercado | G4: Dívida líquida | H4: Minoritários | I4: EV | J4: EBITDA | K4: EBIT | L4: Lucro | M4: Patrimônio | N4: EV/EBITDA | O4: EV/EBIT | P4: P/L | Q4: P/VP
B5: Vale (VALE3) | C5: Mineração | D5: 67.64 | E5: 4072.366 | F5: 275454.84 | G5: 68192 | H5: 4832 | I5: =F5+G5+H5 -> 348478.84 | J5: 51933 | K5: 34110 | L5: 10369 | M5: 196635 | N5: =I5/J5 -> 6.7101619 | O5: =I5/K5 -> 10.216325 | P5: =IF(L5>0,F5/L5,"n.a.") -> 26.565227 | Q5: =F5/M5 -> 1.4008434
B6: CSN (CSNA3) | C6: Siderurgia | D6: 6.36 | E6: 1326.0939 | F6: 8433.9575 | G6: 39079.806 | H6: 3074.044 | I6: =F6+G6+H6 -> 50587.808 | J6: 7727.263 | K6: 3345.416 | L6: -2626.882 | M6: 12166.332 | N6: =I6/J6 -> 6.5466657 | O6: =I6/K6 -> 15.12153 | P6: =IF(L6>0,F6/L6,"n.a.") -> n.a. | Q6: =F6/M6 -> 0.69322105
B7: Gerdau (GGBR4) | C7: Siderurgia | D7: 24.77 | E7: 1963.1806 | F7: 46089.048 | G7: 8117.595 | H7: 190.194 | I7: =F7+G7+H7 -> 54396.837 | J7: 8730.516 | K7: 5034.141 | L7: 2237.081 | M7: 53544.554 | N7: =I7/J7 -> 6.2306554 | O7: =I7/K7 -> 10.805585 | P7: =IF(L7>0,F7/L7,"n.a.") -> 20.602315 | Q7: =F7/M7 -> 0.8607607
B8: Usiminas (USIM5) | C8: Siderurgia | D8: 7.21 | E8: 1230.9427 | F8: 8625.6879 | G8: -599.249 | H8: 2893.937 | I8: =F8+G8+H8 -> 10920.376 | J8: 164.986 | K8: -982.31 | L8: -2320.418 | M8: 20751.154 | N8: =I8/J8 -> 66.189712 | O8: =I8/K8 -> -11.117036 | P8: =IF(L8>0,F8/L8,"n.a.") -> n.a. | Q8: =F8/M8 -> 0.41567268
B9: CSN Mineração (CMIN3) | C9: Mineração | D9: 5.06 | E9: 5402.4354 | F9: 27336.323 | G9: 1025.104 | H9: 0.19 | I9: =F9+G9+H9 -> 28361.617 | J9: 6003.736 | K9: 4642.024 | L9: 2333.063 | M9: 7339.411 | N9: =I9/J9 -> 4.7239947 | O9: =I9/K9 -> 6.1097524 | P9: =IF(L9>0,F9/L9,"n.a.") -> 11.716925 | Q9: =F9/M9 -> 3.7245936
B11: Mediana das comparáveis de VALE3 (sem ela) | N11: =MEDIAN(N6,N7,N8,N9) -> 6.3886606 | O11: =MEDIAN(O6,O7,O8,O9) -> 8.4576685 | P11: =MEDIAN(P6,P7,P8,P9) -> 16.15962 | Q11: =MEDIAN(Q6,Q7,Q8,Q9) -> 0.77699088
B12: Mediana das comparáveis de CSNA3 (sem ela) | N12: =MEDIAN(N5,N7,N8,N9) -> 6.4704086 | O12: =MEDIAN(O5,O7,O8,O9) -> 8.1630386 | P12: =MEDIAN(P5,P7,P8,P9) -> 20.602315 | Q12: =MEDIAN(Q5,Q7,Q8,Q9) -> 1.130802
B13: Mediana das comparáveis de GGBR4 (sem ela) | N13: =MEDIAN(N5,N6,N8,N9) -> 6.6284138 | O13: =MEDIAN(O5,O6,O8,O9) -> 8.1630386 | P13: =MEDIAN(P5,P6,P8,P9) -> 19.141076 | Q13: =MEDIAN(Q5,Q6,Q8,Q9) -> 1.0470322
B15: ="Preço por ação implícito - "&Painel!$D$5 -> Preço por ação implícito - Vale (VALE3) | C15: R$ / ação | D15: Como se calcula
B16: Pelo EV/EBITDA das comparáveis | C16: =IF(INDEX(J5:J7,Painel!$Y$5)>0,(INDEX(N11:N13,Painel!$Y$5)*INDEX(J5:J7,Painel!$Y$5)-INDEX(G5:G7,Painel!$Y$5)-INDEX(H5:H7,Painel!$Y$5))/INDEX(E5:E7,Painel!$Y$5),"n.a.") -> 63.540042 | D16: Mediana × EBITDA da empresa, menos dívida líquida e minoritários, ÷ número de ações.
B17: Pelo EV/EBIT das comparáveis | C17: =IF(INDEX(K5:K7,Painel!$Y$5)>0,(INDEX(O11:O13,Painel!$Y$5)*INDEX(K5:K7,Painel!$Y$5)-INDEX(G5:G7,Painel!$Y$5)-INDEX(H5:H7,Painel!$Y$5))/INDEX(E5:E7,Painel!$Y$5),"n.a.") -> 52.909555 | D17: Mediana × EBIT da empresa, menos dívida líquida e minoritários, ÷ número de ações.
B18: Pelo P/L das comparáveis | C18: =IF(INDEX(L5:L7,Painel!$Y$5)>0,INDEX(P11:P13,Painel!$Y$5)*INDEX(L5:L7,Painel!$Y$5)/INDEX(E5:E7,Painel!$Y$5),"n.a.") -> 41.145393 | D18: Mediana × lucro da empresa ÷ número de ações. Não se aplica com prejuízo.
B19: Pelo P/VP das comparáveis | C19: =INDEX(Q11:Q13,Painel!$Y$5)*INDEX(M5:M7,Painel!$Y$5)/INDEX(E5:E7,Painel!$Y$5) -> 37.517159 | D19: Mediana × patrimônio dos controladores ÷ número de ações.
B20: Pelo fluxo de caixa descontado (aba Valor justo) | C20: ='Valor justo'!D29 -> 94.944606 | D20: Para comparar com os múltiplos.
B21: Preço de mercado | C21: =INDEX(D5:D7,Painel!$Y$5) -> 67.64 | D21: Último fechamento na B3.
B23: EV (valor da empresa) = valor de mercado + dívida líquida + minoritários.
B24: EV/EBITDA: quantos anos de EBITDA o mercado paga pela empresa inteira.
B25: P/L: quantos anos de lucro o mercado paga pela ação. P/VP: quanto paga por real de patrimônio.
B26: A mediana ignora os extremos: a Usiminas, com EBITDA perto de zero, tem EV/EBITDA fora da curva.

Sheet Cenários
B1: ="Cenários - "&Painel!$D$5 -> Cenários - Vale (VALE3)
B2: De onde vem e para onde vai o caixa em cada ano, no cenário em uso. Abaixo, os três cenários lado a lado.
B4: Entradas e saídas de caixa | D4: 2026E | E4: 2027E | F4: 2028E | G4: 2029E | H4: 2030E | I4: O que é
B5: Entradas (cash in)
B6: Caixa gerado pela operação (EBITDA sem equivalência) | D6: =Projeção!D14-Projeção!D13 -> 76996.655 | E6: =Projeção!E14-Projeção!E13 -> 82546.431 | F6: =Projeção!F14-Projeção!F13 -> 88407.998 | G6: =Projeção!G14-Projeção!G13 -> 94596.996 | H6: =Projeção!H14-Projeção!H13 -> 101129.81 | I6: EBITDA sem equivalência: o caixa que a operação produz.
B7: Rendimento do caixa | D7: =Projeção!D17 -> 3896.4744 | E7: =Projeção!E17 -> 3693.0219 | F7: =Projeção!F17 -> 3548.3343 | G7: =Projeção!G17 -> 3488.3238 | H7: =Projeção!H17 -> 3518.9725 | I7: Juros recebidos sobre o caixa aplicado.
B8: Captação líquida de dívida (se positiva) | D8: =MAX(0,Premissas!$D$19) -> 0 | E8: =MAX(0,Premissas!$E$19) -> 0 | F8: =MAX(0,Premissas!$F$19) -> 0 | G8: =MAX(0,Premissas!$G$19) -> 0 | H8: =MAX(0,Premissas!$H$19) -> 0 | I8: Dívida nova que entrou, se a captação líquida foi positiva.
B9: Total de entradas | D9: =D6+D7+D8 -> 80893.129 | E9: =E6+E7+E8 -> 86239.453 | F9: =F6+F7+F8 -> 91956.332 | G9: =G6+G7+G8 -> 98085.32 | H9: =H6+H7+H8 -> 104648.78 | I9: Soma das entradas.
B10: Saídas (cash out)
B11: Imposto de renda e CSLL | D11: =Projeção!D21 -> 19937.026 | E11: =Projeção!E21 -> 21457.323 | F11: =Projeção!F21 -> 23102.069 | G11: =Projeção!G21 -> 24884.963 | H11: =Projeção!H21 -> 26813.191 | I11: Imposto de renda e contribuição social.
B12: Capex | D12: =Projeção!D25 -> 31836.634 | E12: =Projeção!E25 -> 32791.127 | F12: =Projeção!F25 -> 33772.29 | G12: =Projeção!G25 -> 34780.775 | H12: =Projeção!H25 -> 35791.953 | I12: Investimento em ativos.
B13: Investimento em capital de giro | D13: =Projeção!D31 -> 287.37388 | E13: =Projeção!E31 -> 527.23446 | F13: =Projeção!F31 -> 545.66395 | G13: =Projeção!G31 -> 564.73338 | H13: =Projeção!H31 -> 584.4648 | I13: Dinheiro a mais preso em clientes e estoques.
B14: Juros da dívida | D14: =Projeção!D18 -> 5793.592 | E14: =Projeção!E18 -> 5793.592 | F14: =Projeção!F18 -> 5793.592 | G14: =Projeção!G18 -> 5793.592 | H14: =Projeção!H18 -> 5793.592 | I14: Juros pagos sobre a dívida.
B15: Amortização líquida de dívida (se negativa a captação) | D15: =MAX(0,-Premissas!$D$19) -> 0 | E15: =MAX(0,-Premissas!$E$19) -> 0 | F15: =MAX(0,-Premissas!$F$19) -> 0 | G15: =MAX(0,-Premissas!$G$19) -> 0 | H15: =MAX(0,-Premissas!$H$19) -> 0 | I15: Dívida paga, se a captação líquida foi negativa.
B16: Dividendos | D16: =Projeção!D34 -> 25212.142 | E16: =Projeção!E34 -> 27215.984 | F16: =Projeção!F34 -> 29383.855 | G16: =Projeção!G34 -> 31733.815 | H16: =Projeção!H34 -> 34275.333 | I16: Dinheiro entregue aos acionistas.
B17: Total de saídas | D17: =SUM(D11:D16) -> 83066.768 | E17: =SUM(E11:E16) -> 87785.26 | F17: =SUM(F11:F16) -> 92597.47 | G17: =SUM(G11:G16) -> 97757.878 | H17: =SUM(H11:H16) -> 103258.53 | I17: Soma das saídas.
B18: Saldo
B19: Entradas - saídas | D19: =D9-D17 -> -2173.6383 | E19: =E9-E17 -> -1545.8069 | F19: =F9-F17 -> -641.1376 | G19: =G9-G17 -> 327.4425 | H19: =H9-H17 -> 1390.2453 | I19: Entradas − saídas: o que o caixa cresceu ou encolheu no ano.
B20: Caixa no fim do ano | D20: =Projeção!D38 -> 39455.362 | E20: =Projeção!E38 -> 37909.555 | F20: =Projeção!F38 -> 37268.417 | G20: =Projeção!G38 -> 37595.86 | H20: =Projeção!H38 -> 38986.105 | I20: Saldo de caixa no fim do ano (aba Projeção).
B21: Checagem: bate com a variação de caixa da projeção (zero) | D21: =ROUND(D19-Projeção!D35,3) -> 0 | E21: =ROUND(E19-Projeção!E35,3) -> 0 | F21: =ROUND(F19-Projeção!F35,3) -> 0 | G21: =ROUND(G19-Projeção!G35,3) -> 0 | H21: =ROUND(H19-Projeção!H35,3) -> 0 | I21: Tem de ser zero: a conta daqui bate com a da projeção.
B24: Os três cenários da empresa escolhida (calculados pelo modelo) | D24: Pessimista | E24: Moderado | F24: Otimista
B25: Preço justo por ação | D25: =INDEX(D$1:D$72,ROW()+12*Painel!$Y$5) -> 56.920394 | E25: =INDEX(E$1:E$72,ROW()+12*Painel!$Y$5) -> 94.944606 | F25: =INDEX(F$1:F$72,ROW()+12*Painel!$Y$5) -> 159.34302
B26: Valor da empresa (EV) | D26: =INDEX(D$1:D$72,ROW()+12*Painel!$Y$5) -> 277576.68 | E26: =INDEX(E$1:E$72,ROW()+12*Painel!$Y$5) -> 432425.19 | F26: =INDEX(F$1:F$72,ROW()+12*Painel!$Y$5) -> 694679.11
B27: Valor do acionista | D27: =INDEX(D$1:D$72,ROW()+12*Painel!$Y$5) -> 231800.68 | E27: =INDEX(E$1:E$72,ROW()+12*Painel!$Y$5) -> 386649.19 | F27: =INDEX(F$1:F$72,ROW()+12*Painel!$Y$5) -> 648903.11
B28: WACC | D28: =INDEX(D$1:D$72,ROW()+12*Painel!$Y$5) -> 0.14677675 | E28: =INDEX(E$1:E$72,ROW()+12*Painel!$Y$5) -> 0.13117675 | F28: =INDEX(F$1:F$72,ROW()+12*Painel!$Y$5) -> 0.11557675
B29: Crescimento da receita, ao ano | D29: =INDEX(D$1:D$72,ROW()+12*Painel!$Y$5) -> 0 | E29: =INDEX(E$1:E$72,ROW()+12*Painel!$Y$5) -> 0.0378 | F29: =INDEX(F$1:F$72,ROW()+12*Painel!$Y$5) -> 0.0683
B30: Margem EBITDA 2030E | D30: =INDEX(D$1:D$72,ROW()+12*Painel!$Y$5) -> 0.3484 | E30: =INDEX(E$1:E$72,ROW()+12*Painel!$Y$5) -> 0.3936 | F30: =INDEX(F$1:F$72,ROW()+12*Painel!$Y$5) -> 0.4542
B31: Receita 2030E | D31: =INDEX(D$1:D$72,ROW()+12*Painel!$Y$5) -> 218059.14 | E31: =INDEX(E$1:E$72,ROW()+12*Painel!$Y$5) -> 252946.66 | F31: =INDEX(F$1:F$72,ROW()+12*Painel!$Y$5) -> 284018.87
B32: Caixa no fim de 2030E | D32: =INDEX(D$1:D$72,ROW()+12*Painel!$Y$5) -> 40797.533 | E32: =INDEX(E$1:E$72,ROW()+12*Painel!$Y$5) -> 38986.105 | F32: =INDEX(F$1:F$72,ROW()+12*Painel!$Y$5) -> 41622.819
B33: Dívida líquida / EBITDA 2030E | D33: =INDEX(D$1:D$72,ROW()+12*Painel!$Y$5) -> 0.82477267 | E33: =INDEX(E$1:E$72,ROW()+12*Painel!$Y$5) -> 0.64755947 | F33: =INDEX(F$1:F$72,ROW()+12*Painel!$Y$5) -> 0.47932963
B36: Vale (VALE3) | D36: Pessimista | E36: Moderado | F36: Otimista
B37: Preço justo por ação | D37: 56.920394 | E37: 94.944606 | F37: 159.34302
B38: Valor da empresa (EV) | D38: 277576.68 | E38: 432425.19 | F38: 694679.11
B39: Valor do acionista | D39: 231800.68 | E39: 386649.19 | F39: 648903.11
B40: WACC | D40: 0.14677675 | E40: 0.13117675 | F40: 0.11557675
B41: Crescimento da receita, ao ano | D41: 0 | E41: 0.0378 | F41: 0.0683
B42: Margem EBITDA 2030E | D42: 0.3484 | E42: 0.3936 | F42: 0.4542
B43: Receita 2030E | D43: 218059.14 | E43: 252946.66 | F43: 284018.87
B44: Caixa no fim de 2030E | D44: 40797.533 | E44: 38986.105 | F44: 41622.819
B45: Dívida líquida / EBITDA 2030E | D45: 0.82477267 | E45: 0.64755947 | F45: 0.47932963
B48: CSN (CSNA3) | D48: Pessimista | E48: Moderado | F48: Otimista
B49: Preço justo por ação | D49: -8.0403777 | E49: 4.4152557 | F49: 41.787652
B50: Valor da empresa (EV) | D50: 22681.276 | E50: 39198.616 | F50: 88757.923
B51: Valor do acionista | D51: -10662.296 | E51: 5855.0437 | F51: 55414.351
B52: WACC | D52: 0.1153603 | E52: 0.099760299 | F52: 0.084160299
B53: Crescimento da receita, ao ano | D53: 0 | E53: 0.0378 | F53: 0.0778
B54: Margem EBITDA 2030E | D54: 0.1884 | E54: 0.2002 | F54: 0.237
B55: Receita 2030E | D55: 45107.052 | E55: 52323.78 | F55: 60869.139
B56: Caixa no fim de 2030E | D56: 11626.876 | E56: 11366.971 | F56: 13099.858
B57: Dívida líquida / EBITDA 2030E | D57: 4.8595966 | E57: 3.9672268 | F57: 2.7606216
B60: Gerdau (GGBR4) | D60: Pessimista | E60: Moderado | F60: Otimista
B61: Preço justo por ação | D61: 11.939699 | E61: 22.322953 | F61: 42.878448
B62: Valor da empresa (EV) | D62: 28046.768 | E62: 48430.971 | F62: 88785.121
B63: Valor do acionista | D63: 23439.785 | E63: 43823.988 | F63: 84178.138
B64: WACC | D64: 0.1568324 | E64: 0.1412324 | F64: 0.1256324
B65: Crescimento da receita, ao ano | D65: 0 | E65: 0.0378 | F65: 0.061
B66: Margem EBITDA 2030E | D66: 0.1613 | E66: 0.1971 | F66: 0.2506
B67: Receita 2030E | D67: 69544.169 | E67: 80670.618 | F67: 88129.693
B68: Caixa no fim de 2030E | D68: 12250.191 | E68: 13253.607 | F68: 17553.233
B69: Dívida líquida / EBITDA 2030E | D69: 0.17222772 | E69: 0.058398338 | F69: -0.15263919
B73: Preço justo na planilha viva, no cenário em uso | D73: ='Valor justo'!D29 -> 94.944606
B74: Diferença para o comparativo acima (zero sem ajuste manual) | D74: =IF(COUNT(Painel!$G$10:$G$12)=0,ROUND(D73-INDEX(D25:F25,Painel!$Y$9),2),"-") -> 0 | I74: Confere a planilha contra o modelo em Python. Com ajuste manual o cenário já não é nenhum dos três.

Sheet Correlação
B1: Ação contra minério de ferro
B2: A ação anda junto com o minério? A conta usa a variação de um mês para o outro, não o nível do preço: duas séries que só sobem parecem ligadas mesmo sem ter relação.
C4: Contra o minério em dólar | F4: Contra o minério em reais
B5: Variação mensal da ação | C5: Correlação | D5: Sensibilidade | E5: R² | F5: Correlação | G5: Sensibilidade | H5: R²
B6: Vale (VALE3) | C6: =CORREL(L$23:L$90,J$23:J$90) -> 0.69556967 | D6: =SLOPE(L$23:L$90,J$23:J$90) -> 0.55564664 | E6: =RSQ(L$23:L$90,J$23:J$90) -> 0.48381717 | F6: =CORREL(L$23:L$90,K$23:K$90) -> 0.62669532 | G6: =SLOPE(L$23:L$90,K$23:K$90) -> 0.52858334 | H6: =RSQ(L$23:L$90,K$23:K$90) -> 0.39274703
B7: CSN (CSNA3) | C7: =CORREL(M$23:M$90,J$23:J$90) -> 0.54565294 | D7: =SLOPE(M$23:M$90,J$23:J$90) -> 0.72269269 | E7: =RSQ(M$23:M$90,J$23:J$90) -> 0.29773713 | F7: =CORREL(M$23:M$90,K$23:K$90) -> 0.48359418 | G7: =SLOPE(M$23:M$90,K$23:K$90) -> 0.67626542 | H7: =RSQ(M$23:M$90,K$23:K$90) -> 0.23386333
B8: Gerdau (GGBR4) | C8: =CORREL(N$23:N$90,J$23:J$90) -> 0.36927499 | D8: =SLOPE(N$23:N$90,J$23:J$90) -> 0.30062366 | E8: =RSQ(N$23:N$90,J$23:J$90) -> 0.13636402 | F8: =CORREL(N$23:N$90,K$23:K$90) -> 0.34025924 | G8: =SLOPE(N$23:N$90,K$23:K$90) -> 0.29247055 | H8: =RSQ(N$23:N$90,K$23:K$90) -> 0.11577635
B9: ="Escolhida: "&Painel!$D$5 -> Escolhida: Vale (VALE3) | C9: =INDEX(C6:C8,Painel!$Y$5) -> 0.69556967 | D9: =INDEX(D6:D8,Painel!$Y$5) -> 0.55564664 | E9: =INDEX(E6:E8,Painel!$Y$5) -> 0.48381717 | F9: =INDEX(F6:F8,Painel!$Y$5) -> 0.62669532 | G9: =INDEX(G6:G8,Painel!$Y$5) -> 0.52858334 | H9: =INDEX(H6:H8,Painel!$Y$5) -> 0.39274703
B11: Correlação: vai de -1 a 1. Perto de 1, a ação sobe quando o minério sobe; perto de 0, não há relação.
B12: Sensibilidade: quanto a ação costuma variar quando o minério varia 1% (inclinação da reta).
B13: R²: quanto da oscilação da ação o minério explica sozinho. O resto vem de câmbio, juros, custos e notícias.
B14: Período: 2021-01 a 2026-09, 68 variações mensais. Preço médio do mês; ações sem ajuste de dividendos.
B15: Fontes: Banco Mundial (minério 62% Fe, CFR China), Banco Central (dólar PTAX) e B3 (COTAHIST).
B21: Mês | C21: Minério (US$/t) | D21: Dólar (R$) | E21: Minério (R$/t) | F21: VALE3 | G21: CSNA3 | H21: GGBR4 | I21: Ação escolhida | J21: Var. minério US$ | K21: Var. minério R$ | L21: Var. VALE3 | M21: Var. CSNA3 | N21: Var. GGBR4 | O21: Var. ação escolhida | P21: Minério, base 100 | Q21: Ação escolhida, base 100
B22: 2021-01 | C22: 169.6 | D22: 5.3562 | E22: =C22*D22 -> 908.41152 | F22: 94.755263 | G22: 34.929474 | H22: 21.860088 | I22: =CHOOSE(Painel!$Y$5,F22,G22,H22) -> 94.755263 | P22: =C22/C$22*100 -> 100 | Q22: =I22/I$22*100 -> 100
B23: 2021-02 | C23: 163.8 | D23: 5.4165 | E23: =C23*D23 -> 887.2227 | F23: 94.070556 | G23: 33.752222 | H23: 20.391667 | I23: =CHOOSE(Painel!$Y$5,F23,G23,H23) -> 94.070556 | J23: =C23/C22-1 -> -0.034198113 | K23: =E23/E22-1 -> -0.023325134 | L23: =F23/F22-1 -> -0.0072260641 | M23: =G23/G22-1 -> -0.03370367 | N23: =H23/H22-1 -> -0.067173612 | O23: =I23/I22-1 -> -0.0072260641 | P23: =C23/C$22*100 -> 96.580189 | Q23: =I23/I$22*100 -> 99.277394
B24: 2021-03 | C24: 168.2 | D24: 5.6461 | E24: =C24*D24 -> 949.67402 | F24: 97.076522 | G24: 35.731739 | H24: 23.228623 | I24: =CHOOSE(Painel!$Y$5,F24,G24,H24) -> 97.076522 | J24: =C24/C23-1 -> 0.026862027 | K24: =E24/E23-1 -> 0.070389678 | L24: =F24/F23-1 -> 0.031954379 | M24: =G24/G23-1 -> 0.058648491 | N24: =H24/H23-1 -> 0.13912333 | O24: =I24/I23-1 -> 0.031954379 | P24: =C24/C$22*100 -> 99.174528 | Q24: =I24/I$22*100 -> 102.44974
B25: 2021-04 | C25: 179.8 | D25: 5.5621 | E25: =C25*D25 -> 1000.0656 | F25: 106.272 | G25: 45.676 | H25: 26.87125 | I25: =CHOOSE(Painel!$Y$5,F25,G25,H25) -> 106.272 | J25: =C25/C24-1 -> 0.068965517 | K25: =E25/E24-1 -> 0.053061955 | L25: =F25/F24-1 -> 0.094724019 | M25: =G25/G24-1 -> 0.2783033 | N25: =H25/H24-1 -> 0.1568163 | O25: =I25/I24-1 -> 0.094724019 | P25: =C25/C$22*100 -> 106.01415 | Q25: =I25/I$22*100 -> 112.15419
B26: 2021-05 | C26: 207.7 | D26: 5.2911 | E26: =C26*D26 -> 1098.9615 | F26: 112.17952 | G26: 47.63 | H26: 28.734524 | I26: =CHOOSE(Painel!$Y$5,F26,G26,H26) -> 112.17952 | J26: =C26/C25-1 -> 0.15517241 | K26: =E26/E25-1 -> 0.098889405 | L26: =F26/F25-1 -> 0.055588714 | M26: =G26/G25-1 -> 0.042779578 | N26: =H26/H25-1 -> 0.069340794 | O26: =I26/I25-1 -> 0.055588714 | P26: =C26/C$22*100 -> 122.46462 | Q26: =I26/I$22*100 -> 118.3887
B27: 2021-06 | C27: 214.4 | D27: 5.0319 | E27: =C27*D27 -> 1078.8394 | F27: 111.60571 | G27: 44 | H27: 25.952381 | I27: =CHOOSE(Painel!$Y$5,F27,G27,H27) -> 111.60571 | J27: =C27/C26-1 -> 0.032258065 | K27: =E27/E26-1 -> -0.018310114 | L27: =F27/F26-1 -> -0.0051151004 | M27: =G27/G26-1 -> -0.076212471 | N27: =H27/H26-1 -> -0.096822306 | O27: =I27/I26-1 -> -0.0051151004 | P27: =C27/C$22*100 -> 126.41509 | Q27: =I27/I$22*100 -> 117.78313
B28: 2021-07 | C28: 214.1 | D28: 5.1567 | E28: =C28*D28 -> 1104.0495 | F28: 114.06048 | G28: 45.710476 | H28: 25.144444 | I28: =CHOOSE(Painel!$Y$5,F28,G28,H28) -> 114.06048 | J28: =C28/C27-1 -> -0.0013992537 | K28: =E28/E27-1 -> 0.023367807 | L28: =F28/F27-1 -> 0.021994948 | M28: =G28/G27-1 -> 0.038874459 | N28: =H28/H27-1 -> -0.031131498 | O28: =I28/I27-1 -> 0.021994948 | P28: =C28/C$22*100 -> 126.23821 | Q28: =I28/I$22*100 -> 120.37376
B29: 2021-08 | C29: 162.2 | D29: 5.2517 | E29: =C29*D29 -> 851.82574 | F29: 104.82 | G29: 40.593636 | H29: 24.895833 | I29: =CHOOSE(Painel!$Y$5,F29,G29,H29) -> 104.82 | J29: =C29/C28-1 -> -0.24241009 | K29: =E29/E28-1 -> -0.22845329 | L29: =F29/F28-1 -> -0.081013831 | M29: =G29/G28-1 -> -0.1119402 | N29: =H29/H28-1 -> -0.0098873177 | O29: =I29/I28-1 -> -0.081013831 | P29: =C29/C$22*100 -> 95.636792 | Q29: =I29/I$22*100 -> 110.62182
B30: 2021-09 | C30: 124.5 | D30: 5.2797 | E30: =C30*D30 -> 657.32265 | F30: 88.052857 | G30: 31.461905 | H30: 22.180556 | I30: =CHOOSE(Painel!$Y$5,F30,G30,H30) -> 88.052857 | J30: =C30/C29-1 -> -0.2324291 | K30: =E30/E29-1 -> -0.22833671 | L30: =F30/F29-1 -> -0.15996129 | M30: =G30/G29-1 -> -0.22495476 | N30: =H30/H29-1 -> -0.10906555 | O30: =I30/I29-1 -> -0.15996129 | P30: =C30/C$22*100 -> 73.408019 | Q30: =I30/I$22*100 -> 92.926613
B31: 2021-10 | C31: 122.9 | D31: 5.54 | E31: =C31*D31 -> 680.866 | F31: 77.156 | G31: 26.4185 | H31: 22.825 | I31: =CHOOSE(Painel!$Y$5,F31,G31,H31) -> 77.156 | J31: =C31/C30-1 -> -0.012851406 | K31: =E31/E30-1 -> 0.035817037 | L31: =F31/F30-1 -> -0.12375359 | M31: =G31/G30-1 -> -0.16030195 | N31: =H31/H30-1 -> 0.029054477 | O31: =I31/I30-1 -> -0.12375359 | P31: =C31/C$22*100 -> 72.464623 | Q31: =I31/I$22*100 -> 81.426611
B32: 2021-11 | C32: 96.2 | D32: 5.5569 | E32: =C32*D32 -> 534.57378 | F32: 67.4545 | G32: 21.8845 | H32: 21.017083 | I32: =CHOOSE(Painel!$Y$5,F32,G32,H32) -> 67.4545 | J32: =C32/C31-1 -> -0.2172498 | K32: =E32/E31-1 -> -0.21486198 | L32: =F32/F31-1 -> -0.12573876 | M32: =G32/G31-1 -> -0.17162216 | N32: =H32/H31-1 -> -0.07920774 | O32: =I32/I31-1 -> -0.12573876 | P32: =C32/C$22*100 -> 56.721698 | Q32: =I32/I$22*100 -> 71.18813
B33: 2021-12 | C33: 117 | D33: 5.6514 | E33: =C33*D33 -> 661.2138 | F33: 76.93619 | G33: 24.407143 | H33: 23.473016 | I33: =CHOOSE(Painel!$Y$5,F33,G33,H33) -> 76.93619 | J33: =C33/C32-1 -> 0.21621622 | K33: =E33/E32-1 -> 0.23689905 | L33: =F33/F32-1 -> 0.14056424 | M33: =G33/G32-1 -> 0.11527076 | N33: =H33/H32-1 -> 0.11685411 | O33: =I33/I32-1 -> 0.14056424 | P33: =C33/C$22*100 -> 68.985849 | Q33: =I33/I$22*100 -> 81.194635
B34: 2022-01 | C34: 132.5 | D34: 5.5341 | E34: =C34*D34 -> 733.26825 | F34: 83.327619 | G34: 25.311905 | H34: 23.262302 | I34: =CHOOSE(Painel!$Y$5,F34,G34,H34) -> 83.327619 | J34: =C34/C33-1 -> 0.13247863 | K34: =E34/E33-1 -> 0.108973 | L34: =F34/F33-1 -> 0.083074409 | M34: =G34/G33-1 -> 0.037069554 | N34: =H34/H33-1 -> -0.0089768731 | O34: =I34/I33-1 -> 0.083074409 | P34: =C34/C$22*100 -> 78.125 | Q34: =I34/I$22*100 -> 87.939832
... B90: 2026-09 | C90: 97.7 | D90: 5.1447 | E90: =C90*D90 -> 502.63719 | F90: 74.792857 | G90: 6.2257143 | H90: 25.275714 | I90: =CHOOSE(Painel!$Y$5,F90,G90,H90) -> 74.792857 | J90: =C90/C89-1 -> 0.014537902 | K90: =E90/E89-1 -> 0.012864462 | L90: =F90/F89-1 -> -0.0050613186 | M90: =G90/G89-1 -> 0.31002004 | N90: =H90/H89-1 -> 0.046015292 | O90: =I90/I89-1 -> -0.0050613186 | P90: =C90/C$22*100 -> 57.606132 | Q90: =I90/I$22*100 -> 78.932668

Sheet Glossário
B1: Glossário
B2: O que é cada indicador, como se calcula e em que aba aparece.
B4: Termo | C4: O que é | D4: Como se calcula | E4: Onde ver
B5: Receita líquida | C5: Tudo o que a empresa vendeu, sem os impostos sobre a venda. | D5: Vem direto da DRE. | E5: Demonstrativos
B6: EBIT | C6: Lucro da operação, antes de juros e imposto de renda. | D6: Lucro bruto − despesas operacionais. | E6: Demonstrativos
B7: EBITDA | C7: Aproximação do caixa que a operação gera antes de investir e pagar juros. | D7: EBIT + depreciação e amortização. | E7: Demonstrativos
B8: Margem EBITDA | C8: Quanto de cada real vendido vira caixa operacional. | D8: EBITDA ÷ receita. | E8: Demonstrativos
B9: Depreciação e amortização | C9: Desgaste contábil dos ativos. É custo, mas não sai do caixa. | D9: Taxa × ativo fixo do início do ano. | E9: Projeção
B10: NOPAT | C10: Lucro da operação depois do imposto, como se não houvesse dívida. | D10: (EBIT − equivalência) × (1 − alíquota). | E10: FCFF
B11: Capex | C11: Dinheiro investido em máquinas, minas e fábricas. | D11: Percentual da receita. | E11: Projeção
B12: Opex | C12: Despesas para a empresa funcionar: vendas, administração e outras. | D12: Percentual da receita. | E12: Projeção
B13: Capital de giro | C13: Dinheiro preso no dia a dia: o que os clientes devem e o estoque, menos o que se deve a fornecedores. | D13: Contas a receber + estoques − fornecedores. | E13: Projeção
B14: Ciclo de caixa | C14: Quantos dias a empresa financia a operação do próprio bolso. | D14: Prazo de recebimento + prazo de estoque − prazo de pagamento. | E14: Demonstrativos
B15: FCFF | C15: Caixa livre da empresa: o que sobra para credores e acionistas depois de investir. | D15: NOPAT + depreciação − capex − variação do capital de giro. | E15: FCFF
... B38: R² | C38: Quanto da oscilação da ação o minério explica. | D38: Correlação elevada ao quadrado. | E38: Correlação

Sheet Premissas
B1: Premissas
B2: O primeiro bloco mostra a empresa escolhida no Painel e é o que o modelo lê. Para mudar uma premissa, edite as células azuis no bloco da empresa, mais abaixo.
L4: Empresas
B5: ="EM USO: "&INDEX($L$5:$L$7,Painel!$Y$5) -> EM USO: Vale (VALE3) | L5: Vale (VALE3)
B6: Variáveis de cenário | C6: Partida 2026 | D6: Pessimista | E6: Moderado | F6: Otimista | L6: CSN (CSNA3)
B7: Crescimento da receita, ao ano (2027 a 2030) | C7: =INDEX(C$1:C$161,ROW()+39*Painel!$Y$5) -> 0.0209 | D7: =INDEX(D$1:D$161,ROW()+39*Painel!$Y$5) -> 0 | E7: =INDEX(E$1:E$161,ROW()+39*Painel!$Y$5) -> 0.0378 | F7: =INDEX(F$1:F$161,ROW()+39*Painel!$Y$5) -> 0.0683 | L7: Gerdau (GGBR4)
B8: Margem EBITDA em 2030 | C8: =INDEX(C$1:C$161,ROW()+39*Painel!$Y$5) -> 0.3459 | D8: =INDEX(D$1:D$161,ROW()+39*Painel!$Y$5) -> 0.3484 | E8: =INDEX(E$1:E$161,ROW()+39*Painel!$Y$5) -> 0.3936 | F8: =INDEX(F$1:F$161,ROW()+39*Painel!$Y$5) -> 0.4542
B9: WACC: pontos acima ou abaixo do CAPM | D9: =INDEX(D$1:D$161,ROW()+39*Painel!$Y$5) -> 0.0156 | E9: =INDEX(E$1:E$161,ROW()+39*Painel!$Y$5) -> 0 | F9: =INDEX(F$1:F$161,ROW()+39*Painel!$Y$5) -> -0.0156
B11: Iguais nos três cenários, por ano | D11: 2026E | E11: 2027E | F11: 2028E | G11: 2029E | H11: 2030E
B12: Despesas operacionais (% da receita) | D12: =INDEX(D$1:D$161,ROW()+39*Painel!$Y$5) -> 0.083 | E12: =INDEX(E$1:E$161,ROW()+39*Painel!$Y$5) -> 0.0815 | F12: =INDEX(F$1:F$161,ROW()+39*Painel!$Y$5) -> 0.08 | G12: =INDEX(G$1:G$161,ROW()+39*Painel!$Y$5) -> 0.0785 | H12: =INDEX(H$1:H$161,ROW()+39*Painel!$Y$5) -> 0.077
B13: Equivalência patrimonial (R$ milhões) | D13: =INDEX(D$1:D$161,ROW()+39*Painel!$Y$5) -> -1570 | E13: =INDEX(E$1:E$161,ROW()+39*Painel!$Y$5) -> -1570 | F13: =INDEX(F$1:F$161,ROW()+39*Painel!$Y$5) -> -1570 | G13: =INDEX(G$1:G$161,ROW()+39*Painel!$Y$5) -> -1570 | H13: =INDEX(H$1:H$161,ROW()+39*Painel!$Y$5) -> -1570
B14: Investimento - capex (% da receita) | D14: =INDEX(D$1:D$161,ROW()+39*Painel!$Y$5) -> 0.146 | E14: =INDEX(E$1:E$161,ROW()+39*Painel!$Y$5) -> 0.1449 | F14: =INDEX(F$1:F$161,ROW()+39*Painel!$Y$5) -> 0.1438 | G14: =INDEX(G$1:G$161,ROW()+39*Painel!$Y$5) -> 0.1427 | H14: =INDEX(H$1:H$161,ROW()+39*Painel!$Y$5) -> 0.1415
B15: Depreciação (% do ativo fixo inicial) | D15: =INDEX(D$1:D$161,ROW()+39*Painel!$Y$5) -> 0.0569 | E15: =INDEX(E$1:E$161,ROW()+39*Painel!$Y$5) -> 0.0569 | F15: =INDEX(F$1:F$161,ROW()+39*Painel!$Y$5) -> 0.0569 | G15: =INDEX(G$1:G$161,ROW()+39*Painel!$Y$5) -> 0.0569 | H15: =INDEX(H$1:H$161,ROW()+39*Painel!$Y$5) -> 0.0569
B16: Prazo médio de recebimento (dias) | D16: =INDEX(D$1:D$161,ROW()+39*Painel!$Y$5) -> 21.598 | E16: =INDEX(E$1:E$161,ROW()+39*Painel!$Y$5) -> 21.598 | F16: =INDEX(F$1:F$161,ROW()+39*Painel!$Y$5) -> 21.598 | G16: =INDEX(G$1:G$161,ROW()+39*Painel!$Y$5) -> 21.598 | H16: =INDEX(H$1:H$161,ROW()+39*Painel!$Y$5) -> 21.598
B17: Prazo médio de estoque (dias) | D17: =INDEX(D$1:D$161,ROW()+39*Painel!$Y$5) -> 98.067 | E17: =INDEX(E$1:E$161,ROW()+39*Painel!$Y$5) -> 98.067 | F17: =INDEX(F$1:F$161,ROW()+39*Painel!$Y$5) -> 98.067 | G17: =INDEX(G$1:G$161,ROW()+39*Painel!$Y$5) -> 98.067 | H17: =INDEX(H$1:H$161,ROW()+39*Painel!$Y$5) -> 98.067
B18: Prazo médio de pagamento (dias) | D18: =INDEX(D$1:D$161,ROW()+39*Painel!$Y$5) -> 91.9277 | E18: =INDEX(E$1:E$161,ROW()+39*Painel!$Y$5) -> 91.9277 | F18: =INDEX(F$1:F$161,ROW()+39*Painel!$Y$5) -> 91.9277 | G18: =INDEX(G$1:G$161,ROW()+39*Painel!$Y$5) -> 91.9277 | H18: =INDEX(H$1:H$161,ROW()+39*Painel!$Y$5) -> 91.9277
B19: Captação líquida de dívida (R$ milhões) | D19: =INDEX(D$1:D$161,ROW()+39*Painel!$Y$5) -> 0 | E19: =INDEX(E$1:E$161,ROW()+39*Painel!$Y$5) -> 0 | F19: =INDEX(F$1:F$161,ROW()+39*Painel!$Y$5) -> 0 | G19: =INDEX(G$1:G$161,ROW()+39*Painel!$Y$5) -> 0 | H19: =INDEX(H$1:H$161,ROW()+39*Painel!$Y$5) -> 0
B21: Iguais nos três cenários, gerais | D21: Valor
B22: Alíquota de IR e CSLL | D22: =INDEX(D$1:D$161,ROW()+39*Painel!$Y$5) -> 0.34
B23: Juros pagos sobre a dívida (% do saldo inicial) | D23: =INDEX(D$1:D$161,ROW()+39*Painel!$Y$5) -> 0.056
B24: Custo da dívida no WACC, em reais, antes do imposto (Kd) | D24: =INDEX(D$1:D$161,ROW()+39*Painel!$Y$5) -> 0.0715
B25: Rendimento do caixa | D25: =INDEX(D$1:D$161,ROW()+39*Painel!$Y$5) -> 0.0936
B26: Dividendos (% do lucro) | D26: =INDEX(D$1:D$161,ROW()+39*Painel!$Y$5) -> 0.679
B27: Juro sem risco (Rf) | D27: =INDEX(D$1:D$161,ROW()+39*Painel!$Y$5) -> 0.1291
B28: Beta | D28: =INDEX(D$1:D$161,ROW()+39*Painel!$Y$5) -> 0.7558
B29: Prêmio de risco de mercado | D29: =INDEX(D$1:D$161,ROW()+39*Painel!$Y$5) -> 0.0423
B30: Prêmio adicional (tamanho, risco específico) | D30: =INDEX(D$1:D$161,ROW()+39*Painel!$Y$5) -> 0
B31: Peso da dívida na estrutura de capital | D31: =INDEX(D$1:D$161,ROW()+39*Painel!$Y$5) -> 0.2625
B32: Crescimento na perpetuidade (g) | D32: =INDEX(D$1:D$161,ROW()+39*Painel!$Y$5) -> 0.035
B33: Capex na perpetuidade (múltiplo da depreciação) | D33: =INDEX(D$1:D$161,ROW()+39*Painel!$Y$5) -> 1
B34: Outros passivos tratados como dívida (R$ milhões) | D34: =INDEX(D$1:D$161,ROW()+39*Painel!$Y$5) -> 0
B36: Dados de mercado e datas | D36: Valor
B37: Data-base do valuation | D37: =INDEX(D$1:D$161,ROW()+39*Painel!$Y$5) -> 46203
B38: Ações em circulação (milhões) | D38: =INDEX(D$1:D$161,ROW()+39*Painel!$Y$5) -> 4072.366
B39: Preço da ação (R$) | D39: =INDEX(D$1:D$161,ROW()+39*Painel!$Y$5) -> 67.64
B40: Valor de mercado (R$ milhões) | D40: =INDEX(D$1:D$161,ROW()+39*Painel!$Y$5) -> 275454.84
B41: Data do preço | D41: =INDEX(D$1:D$161,ROW()+39*Painel!$Y$5) -> 2026-10-08
B44: Vale (VALE3)
B45: Variáveis de cenário | C45: Partida 2026 | D45: Pessimista | E45: Moderado | F45: Otimista | I45: De onde veio
B46: Crescimento da receita, ao ano (2027 a 2030) | C46: 0.0209 | D46: 0 | E46: 0.0378 | F46: 0.0683 | I46: 2026: nível dos últimos 12 meses (LTM 2T26). Pessimista: receita parada, ou seja, queda real. Moderado: inflação esperada no Focus para 2027-2030, crescimento real zero. Otimista: crescimento médio da receita de 2018 a 2025 (6,8% ao ano).
B47: Margem EBITDA em 2030 | C47: 0.3459 | D47: 0.3484 | E47: 0.3936 | F47: 0.4542 | I47: 2026: nível dos últimos 12 meses (LTM 2T26). Daí até 2030 em linha reta. Faixa: margem EBITDA de 2021 a 2025, sem perdas por recuperabilidade. Pessimista é o segundo pior ano, moderado a mediana e otimista o segundo melhor.
B48: WACC: pontos acima ou abaixo do CAPM | D48: 0.0156 | E48: 0 | F48: -0.0156 | I48: Moderado: o WACC que sai do CAPM. O juro prefixado longo andou de 12,2% a 15,3% nos últimos dois anos; pessimista e otimista deslocam o WACC em metade dessa amplitude.
B50: Iguais nos três cenários, por ano | D50: 2026E | E50: 2027E | F50: 2028E | G50: 2029E | H50: 2030E | I50: De onde veio
B51: Despesas operacionais (% da receita) | D51: 0.083 | E51: 0.0815 | F51: 0.08 | G51: 0.0785 | H51: 0.077 | I51: Vendas, administrativas e outras, sem perdas por recuperabilidade. Do nível dos últimos 12 meses até a mediana de 2021-2025.
B52: Equivalência patrimonial (R$ milhões) | D52: -1570 | E52: -1570 | F52: -1570 | G52: -1570 | H52: -1570 | I52: Mediana de 2021-2025, mantida.
B53: Investimento - capex (% da receita) | D53: 0.146 | E53: 0.1449 | F53: 0.1438 | G53: 0.1427 | H53: 0.1415 | I53: Do nível dos últimos 12 meses até a mediana de 2021-2025.
B54: Depreciação (% do ativo fixo inicial) | D54: 0.0569 | E54: 0.0569 | F54: 0.0569 | G54: 0.0569 | H54: 0.0569 | I54: Mediana de 2021-2025, mantida.
B55: Prazo médio de recebimento (dias) | D55: 21.598 | E55: 21.598 | F55: 21.598 | G55: 21.598 | H55: 21.598 | I55: Prazo de 2025, mantido.
B56: Prazo médio de estoque (dias) | D56: 98.067 | E56: 98.067 | F56: 98.067 | G56: 98.067 | H56: 98.067 | I56: Prazo de 2025, mantido.
B57: Prazo médio de pagamento (dias) | D57: 91.9277 | E57: 91.9277 | F57: 91.9277 | G57: 91.9277 | H57: 91.9277 | I57: Prazo de 2025, mantido.
B58: Captação líquida de dívida (R$ milhões) | D58: 0 | E58: 0 | F58: 0 | G58: 0 | H58: 0 | I58: Dívida bruta mantida no nível de 2025.
B60: Iguais nos três cenários, gerais | D60: Valor | I60: De onde veio
B61: Alíquota de IR e CSLL | D61: 0.34 | I61: Alíquota nominal: IRPJ 25% + CSLL 9%.
B62: Juros pagos sobre a dívida (% do saldo inicial) | D62: 0.056 | I62: Custo médio de 5,6% ao ano em dólar, depois de swaps (formulário 6-K do 2T26, SEC).
B63: Custo da dívida no WACC, em reais, antes do imposto (Kd) | D63: 0.0715 | I63: Custo médio de 5,6% ao ano em dólar, depois de swaps (formulário 6-K do 2T26, SEC). A parte em dólar foi trazida para reais pela diferença de inflação (3,5% no Brasil, 2,0% nos EUA).
B64: Rendimento do caixa | D64: 0.0936 | I64: Mediana 2023-2025 da receita financeira sobre o caixa médio.
B65: Dividendos (% do lucro) | D65: 0.679 | I65: Mediana 2021-2025 de dividendos pagos sobre lucro, limitada a 0-100%.
B66: Juro sem risco (Rf) | D66: 0.1291 | I66: Tesouro prefixado de dez anos (em reais, nominal).
B67: Beta | D67: 0.7558 | I67: Regressão de 5 anos, retornos semanais contra o BOVA11, preços sem ajuste de proventos. Beta de 2 anos: 0,64.
B68: Prêmio de risco de mercado | D68: 0.0423 | I68: Damodaran, mercado maduro. O risco-país já está no juro em reais.
B69: Prêmio adicional (tamanho, risco específico) | D69: 0 | I69: Sem prêmio adicional.
B70: Peso da dívida na estrutura de capital | D70: 0.2625 | I70: Dívida bruta do 2T26 sobre dívida mais valor de mercado.
B71: Crescimento na perpetuidade (g) | D71: 0.035 | I71: IPCA esperado para 2030: crescimento real zero.
B72: Capex na perpetuidade (múltiplo da depreciação) | D72: 1 | I72: Na perpetuidade a empresa reinveste o que deprecia.
B73: Outros passivos tratados como dívida (R$ milhões) | D73: 0 | I73: Nenhum. Provisões (barragens, contingências) não entram como dívida.
B75: Dados de mercado e datas | D75: Valor | I75: De onde veio
B76: Data-base do valuation | D76: 46203 | I76: Último balanço trimestral (ITR).
B77: Ações em circulação (milhões) | D77: 4072.366 | I77: CVM, composição do capital, sem ações em tesouraria.
B78: Preço da ação (R$) | D78: 67.64 | I78: B3, último fechamento.
B79: Valor de mercado (R$ milhões) | D79: 275454.84 | I79: Ações em circulação pelo preço de cada classe.
B80: Data do preço | D80: 2026-10-08 | I80: Pregão do preço acima.
B83: CSN (CSNA3)
B84: Variáveis de cenário | C84: Partida 2026 | D84: Pessimista | E84: Moderado | F84: Otimista | I84: De onde veio
B85: Crescimento da receita, ao ano (2027 a 2030) | C85: 0.0069 | D85: 0 | E85: 0.0378 | F85: 0.0778 | I85: 2026: nível dos últimos 12 meses (LTM 2T26). Pessimista: receita parada, ou seja, queda real. Moderado: inflação esperada no Focus para 2027-2030, crescimento real zero. Otimista: crescimento médio da receita de 2018 a 2025 (10,0% ao ano), limitado a 4% acima da inflação porque parte veio de aquisições.
B86: Margem EBITDA em 2030 | C86: 0.1713 | D86: 0.1884 | E86: 0.2002 | F86: 0.237 | I86: 2026: nível dos últimos 12 meses (LTM 2T26). Daí até 2030 em linha reta. Faixa: margem EBITDA de 2021 a 2025, sem perdas por recuperabilidade. Pessimista é o segundo pior ano, moderado a mediana e otimista o segundo melhor.
B87: WACC: pontos acima ou abaixo do CAPM | D87: 0.0156 | E87: 0 | F87: -0.0156 | I87: Moderado: o WACC que sai do CAPM. O juro prefixado longo andou de 12,2% a 15,3% nos últimos dois anos; pessimista e otimista deslocam o WACC em metade dessa amplitude.
B89: Iguais nos três cenários, por ano | D89: 2026E | E89: 2027E | F89: 2028E | G89: 2029E | H89: 2030E | I89: De onde veio
B90: Despesas operacionais (% da receita) | D90: 0.2146 | E90: 0.2001 | F90: 0.1857 | G90: 0.1713 | H90: 0.1569 | I90: Vendas, administrativas e outras, sem perdas por recuperabilidade. Do nível dos últimos 12 meses até a mediana de 2021-2025.
B91: Equivalência patrimonial (R$ milhões) | D91: 351.131 | E91: 351.131 | F91: 351.131 | G91: 351.131 | H91: 351.131 | I91: Mediana de 2021-2025, mantida.
B92: Investimento - capex (% da receita) | D92: 0.1326 | E92: 0.1237 | F92: 0.1148 | G92: 0.1059 | H92: 0.097 | I92: Do nível dos últimos 12 meses até a mediana de 2021-2025.
B93: Depreciação (% do ativo fixo inicial) | D93: 0.0983 | E93: 0.0983 | F93: 0.0983 | G93: 0.0983 | H93: 0.0983 | I93: Mediana de 2021-2025, mantida.
B94: Prazo médio de recebimento (dias) | D94: 19.5303 | E94: 19.5303 | F94: 19.5303 | G94: 19.5303 | H94: 19.5303 | I94: Prazo de 2025, mantido.
B95: Prazo médio de estoque (dias) | D95: 135.0709 | E95: 135.0709 | F95: 135.0709 | G95: 135.0709 | H95: 135.0709 | I95: Prazo de 2025, mantido.
B96: Prazo médio de pagamento (dias) | D96: 92.5353 | E96: 92.5353 | F96: 92.5353 | G96: 92.5353 | H96: 92.5353 | I96: Prazo de 2025, mantido.
B97: Captação líquida de dívida (R$ milhões) | D97: 0 | E97: 0 | F97: 0 | G97: 0 | H97: 0 | I97: Dívida bruta mantida no nível de 2025.
B99: Iguais nos três cenários, gerais | D99: Valor | I99: De onde veio
B100: Alíquota de IR e CSLL | D100: 0.34 | I100: Alíquota nominal: IRPJ 25% + CSLL 9%.
B101: Juros pagos sobre a dívida (% do saldo inicial) | D101: 0.0777 | I101: A CSN não divulga custo médio. Juros pagos em 2025 (R$ 4.268 mi, linha "Juros pagos" do fluxo de caixa na CVM) sobre a dívida bruta média do ano.
B102: Custo da dívida no WACC, em reais, antes do imposto (Kd) | D102: 0.1291 | I102: A empresa não divulga custo médio: mantido o piso, a taxa do Tesouro prefixado de dez anos, sem spread de crédito.
B103: Rendimento do caixa | D103: 0.0772 | I103: Mediana 2023-2025 da receita financeira sobre o caixa médio.
B104: Dividendos (% do lucro) | D104: 0.242 | I104: Mediana 2021-2025 de dividendos pagos sobre lucro, limitada a 0-100%.
B105: Juro sem risco (Rf) | D105: 0.1291 | I105: Tesouro prefixado de dez anos (em reais, nominal).
B106: Beta | D106: 1.483 | I106: Regressão de 5 anos, retornos semanais contra o BOVA11, preços sem ajuste de proventos. Beta de 2 anos: 1,48.
B107: Prêmio de risco de mercado | D107: 0.0423 | I107: Damodaran, mercado maduro. O risco-país já está no juro em reais.
B108: Prêmio adicional (tamanho, risco específico) | D108: 0 | I108: Sem prêmio adicional.
B109: Peso da dívida na estrutura de capital | D109: 0.8635 | I109: Dívida bruta do 2T26 sobre dívida mais valor de mercado.
B110: Crescimento na perpetuidade (g) | D110: 0.035 | I110: IPCA esperado para 2030: crescimento real zero.
B111: Capex na perpetuidade (múltiplo da depreciação) | D111: 1 | I111: Na perpetuidade a empresa reinveste o que deprecia.
B112: Outros passivos tratados como dívida (R$ milhões) | D112: 0 | I112: Nenhum. Provisões (barragens, contingências) não entram como dívida.
B114: Dados de mercado e datas | D114: Valor | I114: De onde veio
...

Sheet Dados
B1: Dados da CVM
B2: Demonstrações consolidadas entregues à CVM (DFP e ITR), em R$ milhões. A aba Demonstrativos mostra o bloco da empresa escolhida no Painel.
B4: Vale (VALE3)
B5: R$ milhões | C5: 2018 | D5: 2019 | E5: 2020 | F5: 2021 | G5: 2022 | H5: 2023 | I5: 2024 | J5: 2025 | K5: LTM 2T26
B6: Receita líquida | C6: 134483.13 | D6: 148639.92 | E6: 208528.76 | F6: 293524 | G6: 226508 | H6: 208066 | I6: 206005 | J6: 213595 | K6: 218069
B7: Custo dos produtos vendidos | C7: -81200.904 | D7: -83835.563 | E7: -98567.494 | F7: -117267 | G7: -124195 | H7: -120016 | I7: -131318 | J7: -138887 | K7: -141911
B8: Lucro bruto | C8: 53282.222 | D8: 64804.358 | E8: 109961.26 | F8: 176257 | G8: 102313 | H8: 88050 | I8: 74687 | J8: 74708 | K8: 76158
B9: Despesas com vendas | C9: 0 | D9: 0 | E9: 0 | F9: 0 | G9: 0 | H9: 0 | I9: 0 | J9: 0 | K9: 0
B10: Despesas gerais e administrativas | C10: -1916.765 | D10: -1924.308 | E10: -2856.913 | F10: -2601 | G10: -2658 | H10: -2758 | I10: -3397 | J10: -3566 | K10: -3667
B11: Perdas por recuperabilidade de ativos (impairment) | C11: -3523.458 | D11: -20762.371 | E11: -11818.792 | F11: -2352 | G11: 3833 | H11: -1317 | I11: 510 | J11: -25147 | K11: -23490
B12: Total de despesas/receitas operacionais | C12: -10106.478 | D12: -62564.583 | E12: -57893.647 | F12: -34922 | G12: -11987 | H12: -22778 | I12: -19228 | J12: -42739 | K12: -42048
B13: Equivalência patrimonial | C13: -693.486 | D13: -2683.903 | E13: -5435.93 | F13: -6947 | G13: 1616 | H13: -5434 | I13: -1570 | J13: -1170 | K13: -453
B14: EBIT (resultado antes do financeiro e dos tributos) | C14: 43175.744 | D14: 2239.775 | E14: 52067.618 | F14: 141335 | G14: 90326 | H14: 65272 | I14: 55459 | J14: 31969 | K14: 34110
B15: Resultado financeiro | C15: -18057.519 | D15: -13444.786 | E15: -24140.63 | F15: 17812 | G15: 11378 | H15: -9718 | I15: -21235 | J15: -5276 | K15: -9699
B16: Lucro antes dos tributos | C16: 25118.225 | D16: -11205.011 | E16: 27926.988 | F16: 159147 | G16: 101704 | H16: 55554 | I16: 34224 | J16: 26693 | K16: 24411
B17: Imposto de renda e CSLL | C17: 965.98 | D17: 2508.971 | E17: -3024.647 | F17: -25320 | G17: -15185 | H17: -15000 | I17: -3793 | J17: -14882 | K17: -15720
... B38: Participação de não controladores | C38: 3279.552 | D38: -4330.947 | E38: -4798.995 | F38: 4655 | G38: 7782 | H38: 7360 | I38: 6948 | J38: 4627 | K38: 4832
B40: CSN (CSNA3)
B41: R$ milhões | C41: 2018 | D41: 2019 | E41: 2020 | F41: 2021 | G41: 2022 | H41: 2023 | I41: 2024 | J41: 2025 | K41: LTM 2T26
B42: Receita líquida | C42: 22968.885 | D42: 25436.417 | E42: 30064.02 | F42: 47912.039 | G42: 44362.12 | H42: 45437.95 | I42: 43687.46 | J42: 44797.946 | K42: 45106.972
B43: Custo dos produtos vendidos | C43: -16105.657 | D43: -17263.264 | E43: -19124.901 | F43: -25837.475 | G43: -31054.016 | H43: -33475.189 | I43: -31990.696 | J43: -32404.221 | K43: -32517.962
B44: Lucro bruto | C44: 6863.228 | D44: 8173.153 | E44: 10939.119 | F44: 22074.564 | G44: 13308.104 | H44: 11962.761 | I44: 11696.764 | J44: 12393.725 | K44: 12589.01
B45: Despesas com vendas | C45: -2263.688 | D45: -2342.805 | E45: -2004.417 | F45: -2372.298 | G45: -2575.818 | H45: -3729.089 | I45: -5453.297 | J45: -5033.148 | K45: -5210.199
B46: Despesas gerais e administrativas | C46: -494.023 | D46: -511.065 | E46: -504.458 | F46: -587.148 | G46: -674.119 | H46: -760.894 | I46: -855.999 | J46: -979.164 | K46: -1009.541
B47: Perdas por recuperabilidade de ativos (impairment) | C47: 0 | D47: 0 | E47: 0 | F47: 0 | G47: 0 | H47: 0 | I47: 0 | J47: 0 | K47: 0
B48: Total de despesas/receitas operacionais | C48: 83.332 | D48: -4631.236 | E48: -5224.682 | F48: -1534.602 | G48: -5666.642 | H48: -6776.012 | I48: -7426.742 | J48: -7577.051 | K48: -9243.594
B49: Equivalência patrimonial | C49: 135.706 | D49: 125.715 | E49: 71.755 | F49: 182.504 | G49: 237.917 | H49: 351.131 | I49: 448.048 | J49: 518.744 | K49: 435.292
B50: EBIT (resultado antes do financeiro e dos tributos) | C50: 6946.56 | D50: 3541.917 | E50: 5714.437 | F50: 20539.962 | G50: 7641.462 | H50: 5186.749 | I50: 4270.022 | J50: 4816.674 | K50: 3345.416
B51: Resultado financeiro | C51: -1495.643 | D51: -2131.184 | E51: -796.311 | F51: -1944.184 | G51: -3515.025 | H51: -4151.382 | I51: -5813.371 | J51: -6496.192 | K51: -5895.433
B52: Lucro antes dos tributos | C52: 5450.917 | D52: 1410.733 | E52: 4918.126 | F52: 18595.778 | G52: 4126.437 | H52: 1035.367 | I52: -1543.349 | J52: -1679.518 | K52: -2550.017
B53: Imposto de renda e CSLL | C53: -250.334 | D53: 833.778 | E53: -625.508 | F53: -5000.157 | G53: -1958.739 | H53: -632.718 | I53: 5.208 | J53: 172.792 | K53: 577.159
... B74: Participação de não controladores | C74: 1310.705 | D74: 1187.388 | E74: 1338.054 | F74: 3059.391 | G74: 2326.577 | H74: 2184.163 | I74: 3187.678 | J74: 2860.291 | K74: 3074.044
B76: Gerdau (GGBR4)
B77: R$ milhões | C77: 2018 | D77: 2019 | E77: 2020 | F77: 2021 | G77: 2022 | H77: 2023 | I77: 2024 | J77: 2025 | K77: LTM 2T26
B78: Receita líquida | C78: 46159.478 | D78: 39644.01 | E78: 43814.661 | F78: 78345.081 | G78: 82412.21 | H78: 68916.447 | I78: 67026.656 | J78: 69858.532 | K78: 69543.739
B79: Custo dos produtos vendidos | C79: -40010.1 | D79: -35440.726 | E79: -37884.102 | F79: -57527.721 | G79: -63661.156 | H79: -57583.992 | I79: -57823.416 | J79: -61891.039 | K79: -60430.291
B80: Lucro bruto | C80: 6149.378 | D80: 4203.284 | E80: 5930.559 | F80: 20817.36 | G80: 18751.054 | H80: 11332.455 | I80: 9203.24 | J80: 7967.493 | K80: 9113.448
B81: Despesas com vendas | C81: -580.345 | D81: -476.339 | E81: -512.95 | F81: -715.83 | G81: -733.026 | H81: -716.195 | I81: -762.56 | J81: -782.351 | K81: -757.79
B82: Despesas gerais e administrativas | C82: -1082.449 | D82: -954.117 | E82: -1017.435 | F82: -1390.121 | G82: -1454.592 | H82: -1491.441 | I82: -1404.059 | J82: -1338.443 | K82: -1302.351
B83: Perdas por recuperabilidade de ativos (impairment) | C83: 0 | D83: 0 | E83: -411.925 | F83: 0 | G83: 0 | H83: 0 | I83: -199.627 | J83: -1964.504 | K83: -1964.504
B84: Total de despesas/receitas operacionais | C84: -2102.152 | D84: -1019.35 | E84: -736.174 | F84: 205.662 | G84: -999.601 | H84: -879.728 | I84: -1716.038 | J84: -4228.425 | K84: -4079.307
B85: Equivalência patrimonial | C85: 10.141 | D85: -17.05 | E85: 152.569 | F85: 563.158 | G85: 1151.827 | H85: 827.606 | I85: 464.467 | J85: 95.622 | K85: 196.604
B86: EBIT (resultado antes do financeiro e dos tributos) | C86: 4047.226 | D86: 3183.934 | E86: 5194.385 | F86: 21023.022 | G86: 17751.453 | H86: 10452.727 | I86: 7487.202 | J86: 3739.068 | K86: 5034.141
B87: Resultado financeiro | C87: -1889.795 | D87: -1509.214 | E87: -1698.707 | F87: -750.454 | G87: -1892.426 | H87: -1106.122 | I87: -2023.487 | J87: -1214.621 | K87: -1200.23
B88: Lucro antes dos tributos | C88: 2157.431 | D88: 1674.72 | E88: 3495.678 | F88: 20272.568 | G88: 15859.027 | H88: 9346.605 | I88: 5463.715 | J88: 2524.447 | K88: 3833.911
B89: Imposto de renda e CSLL | C89: 168.951 | D89: -457.833 | E89: -1107.624 | F89: -4713.63 | G89: -4379.475 | H89: -1809.622 | I89: -864.653 | J89: -1106.009 | K89: -1558.373
... B110: Participação de não controladores | C110: 207.967 | D110: 217.426 | E110: 224.939 | F110: 211.367 | G110: 181.999 | H110: 179.904 | I110: 225.027 | J110: 213.096 | K110: 190.194
